Workbook

Sheet README
A1: Construction cash-flow forecast — advance, retention, S-curve, fiscal years (Module 10, Lesson 6)
A3: Yellow cells with blue bold text = INPUTS you may change.
A4: Green cells = key RESULTS (formulas — do not overwrite).
A6: WHAT THIS MODEL DOES
A7: Turns a construction contract into a monthly payment forecast for the Employer (MEWRE) and a fiscal-year budget request. Gross work value comes either from an S-curve (cosine profile) or from a milestone payment schedule. From each interim payment certificate it deducts advance-payment recovery and retention, adds the advance at signature and the two retention releases, and sums net payments by fiscal year.
A8: Default payment terms follow FIDIC 2017 conventions (advance recovered by amortisation starting when certified work exceeds 10% of the Accepted Contract Amount, at 25% of each IPC; retention at a percentage of each IPC up to a limit; half released at Taking-Over, half at the end of the Defects Notification Period). Your contract's Particular Conditions / Contract Data override these.
A9: Fiscal year: Kuwait's state budget year is assumed to start in April (FY = 1 April to 31 March). This is widely reported but is NOT sourced in the course research brief — confirm with the Ministry of Finance budget circular. Change 'FY start month' if needed.
A10: Sheets: Inputs -> Milestones (optional schedule) -> Monthly (months 0..48) -> FY Budget -> Contingency (commitment vs budget, contingency drawdown log).
A11: EXERCISES
A12: 1. Base case (KWD 45.0 m, 24 months from June 2026, S-curve): confirm FY2026/27 net payments KWD 14.282 m, FY2027/28 KWD 26.755 m.
A13: 2. The contractor asks to raise the advance from 10% to 20%. What changes in FY2026/27 cash need and in MEWRE's exposure? What security must be increased?
A14: 3. Switch basis to milestones (Inputs basis = 2). Compare the FY split with the S-curve. Which is more realistic for a substation and OHL package?
... A19: Currency convention: USD for IPP economics, KWD for ministry budgets; assumed 1 KWD = 3.25 USD (change in Inputs where shown).

Sheet Inputs
A1: Inputs — contract payment terms
A4: Input | B4: Value | C4: Unit | D4: Note / typical range
A5: Accepted Contract Amount | B5: 45 | C5: KWD m
A6: Month 0 (signature / advance date) | B6: 46174 | C6: date
A7: Time for completion | B7: 24 | C7: months | D7: Taking-Over assumed at month T
A8: Advance payment | B8: 0.1 | C8: % of contract | D8: Paid against an advance payment guarantee
A9: Recovery starts when certified work exceeds | B9: 0.1 | C9: % of contract | D9: FIDIC 2017 default 10%
A10: Amortisation rate | B10: 0.25 | C10: % of each IPC | D10: FIDIC 2017 default 25%
A11: Retention rate | B11: 0.1 | C11: % of each IPC
A12: Retention limit | B12: 0.05 | C12: % of contract
A13: Defects Notification Period | B13: 12 | C13: months | D13: Max 24 in this sheet
A14: Gross value basis (1 = S-curve, 2 = milestones) | B14: 1 | C14: switch
A15: Fiscal year start month | B15: 4 | C15: month (1–12) | D15: Assumed April — verify

Sheet Milestones
A1: Milestone payment schedule (used when basis = 2)
A2: Percentages must total 100%.
A4: # | B4: Milestone | C4: % of contract | D4: Month achieved | E4: Value (KWD m)
A5: 1 | B5: Approved route survey, design basis and SLD | C5: 0.05 | D5: 3 | E5: =C5*'Inputs'!$B$5
A6: 2 | B6: Approved detailed design (towers, foundations, GIS layout) | C6: 0.05 | D6: 6 | E6: =C6*'Inputs'!$B$5
A7: 3 | B7: Tower steel and conductor delivered to site (50%) | C7: 0.1 | D7: 9 | E7: =C7*'Inputs'!$B$5
A8: 4 | B8: Foundations 50% complete | C8: 0.1 | D8: 10 | E8: =C8*'Inputs'!$B$5
A9: 5 | B9: GIS and transformers factory acceptance tests passed | C9: 0.1 | D9: 12 | E9: =C9*'Inputs'!$B$5
A10: 6 | B10: Tower steel and conductor delivered (100%) | C10: 0.1 | D10: 13 | E10: =C10*'Inputs'!$B$5
A11: 7 | B11: Towers erected 100% | C11: 0.1 | D11: 16 | E11: =C11*'Inputs'!$B$5
A12: 8 | B12: GIS and transformers delivered and installed | C12: 0.15 | D12: 18 | E12: =C12*'Inputs'!$B$5
A13: 9 | B13: Stringing complete | C13: 0.1 | D13: 20 | E13: =C13*'Inputs'!$B$5
A14: 10 | B14: Pre-commissioning and protection tests complete | C14: 0.05 | D14: 22 | E14: =C14*'Inputs'!$B$5
A15: 11 | B15: Energization and Taking-Over | C15: 0.1 | D15: 24 | E15: =C15*'Inputs'!$B$5
B16: Total (must be 100%) | C16: =SUM(C5:C15) | E16: =SUM(E5:E15)

Sheet Monthly
A1: Monthly payment forecast (KWD m) — formulas
A2: Net payment = gross IPC + advance - advance recovery - retention + retention release.
A4: Month | B4: Date | C4: Fiscal year | D4: S-curve cum. % | E4: Gross (S-curve) | F4: Gross (milestones) | G4: Gross IPC used | H4: Cum. gross | I4: Advance paid | J4: Advance recovery | K4: Retention held | L4: Retention release | M4: Net payment | N4: Cum. net
A5: 0 | B5: =EDATE('Inputs'!$B$6,A5) | C5: =IF(MONTH(B5)>='Inputs'!$B$15,YEAR(B5)&"/"&RIGHT(YEAR(B5)+1,2),(YEAR(B5)-1)&"/"&RIGHT(YEAR(B5),2)) | D5: =IF(A5>='Inputs'!$B$7,1,(1-COS(PI()*A5/'Inputs'!$B$7))/2) | E5: =0 | F5: =SUMIF(Milestones!$D$5:$D$15,A5,Milestones!$E$5:$E$15) | G5: =IF('Inputs'!$B$14=1,E5,F5) | H5: =G5 | I5: =IF(A5=0,'Inputs'!$B$8*'Inputs'!$B$5,0) | J5: =MAX(0,IF(A5='Inputs'!$B$7,'Inputs'!$B$8*'Inputs'!$B$5-0,IF(H5>'Inputs'!$B$9*'Inputs'!$B$5,MIN('Inputs'!$B$10*G5,'Inputs'!$B$8*'Inputs'!$B$5-0),0))) | K5: =MAX(0,MIN('Inputs'!$B$11*G5,'Inputs'!$B$12*'Inputs'!$B$5-0)) | L5: =IF(A5='Inputs'!$B$7,SUM(K$5:K$53)/2,0)+IF(A5='Inputs'!$B$7+'Inputs'!$B$13,SUM(K$5:K$53)/2,0) | M5: =G5+I5-J5-K5+L5 | N5: =M5
A6: 1 | B6: =EDATE('Inputs'!$B$6,A6) | C6: =IF(MONTH(B6)>='Inputs'!$B$15,YEAR(B6)&"/"&RIGHT(YEAR(B6)+1,2),(YEAR(B6)-1)&"/"&RIGHT(YEAR(B6),2)) | D6: =IF(A6>='Inputs'!$B$7,1,(1-COS(PI()*A6/'Inputs'!$B$7))/2) | E6: ='Inputs'!$B$5*(D6-D5) | F6: =SUMIF(Milestones!$D$5:$D$15,A6,Milestones!$E$5:$E$15) | G6: =IF('Inputs'!$B$14=1,E6,F6) | H6: =H5+G6 | I6: =IF(A6=0,'Inputs'!$B$8*'Inputs'!$B$5,0) | J6: =MAX(0,IF(A6='Inputs'!$B$7,'Inputs'!$B$8*'Inputs'!$B$5-SUM(J$5:J5),IF(H6>'Inputs'!$B$9*'Inputs'!$B$5,MIN('Inputs'!$B$10*G6,'Inputs'!$B$8*'Inputs'!$B$5-SUM(J$5:J5)),0))) | K6: =MAX(0,MIN('Inputs'!$B$11*G6,'Inputs'!$B$12*'Inputs'!$B$5-SUM(K$5:K5))) | L6: =IF(A6='Inputs'!$B$7,SUM(K$5:K$53)/2,0)+IF(A6='Inputs'!$B$7+'Inputs'!$B$13,SUM(K$5:K$53)/2,0) | M6: =G6+I6-J6-K6+L6 | N6: =N5+M6
A7: 2 | B7: =EDATE('Inputs'!$B$6,A7) | C7: =IF(MONTH(B7)>='Inputs'!$B$15,YEAR(B7)&"/"&RIGHT(YEAR(B7)+1,2),(YEAR(B7)-1)&"/"&RIGHT(YEAR(B7),2)) | D7: =IF(A7>='Inputs'!$B$7,1,(1-COS(PI()*A7/'Inputs'!$B$7))/2) | E7: ='Inputs'!$B$5*(D7-D6) | F7: =SUMIF(Milestones!$D$5:$D$15,A7,Milestones!$E$5:$E$15) | G7: =IF('Inputs'!$B$14=1,E7,F7) | H7: =H6+G7 | I7: =IF(A7=0,'Inputs'!$B$8*'Inputs'!$B$5,0) | J7: =MAX(0,IF(A7='Inputs'!$B$7,'Inputs'!$B$8*'Inputs'!$B$5-SUM(J$5:J6),IF(H7>'Inputs'!$B$9*'Inputs'!$B$5,MIN('Inputs'!$B$10*G7,'Inputs'!$B$8*'Inputs'!$B$5-SUM(J$5:J6)),0))) | K7: =MAX(0,MIN('Inputs'!$B$11*G7,'Inputs'!$B$12*'Inputs'!$B$5-SUM(K$5:K6))) | L7: =IF(A7='Inputs'!$B$7,SUM(K$5:K$53)/2,0)+IF(A7='Inputs'!$B$7+'Inputs'!$B$13,SUM(K$5:K$53)/2,0) | M7: =G7+I7-J7-K7+L7 | N7: =N6+M7
A8: 3 | B8: =EDATE('Inputs'!$B$6,A8) | C8: =IF(MONTH(B8)>='Inputs'!$B$15,YEAR(B8)&"/"&RIGHT(YEAR(B8)+1,2),(YEAR(B8)-1)&"/"&RIGHT(YEAR(B8),2)) | D8: =IF(A8>='Inputs'!$B$7,1,(1-COS(PI()*A8/'Inputs'!$B$7))/2) | E8: ='Inputs'!$B$5*(D8-D7) | F8: =SUMIF(Milestones!$D$5:$D$15,A8,Milestones!$E$5:$E$15) | G8: =IF('Inputs'!$B$14=1,E8,F8) | H8: =H7+G8 | I8: =IF(A8=0,'Inputs'!$B$8*'Inputs'!$B$5,0) | J8: =MAX(0,IF(A8='Inputs'!$B$7,'Inputs'!$B$8*'Inputs'!$B$5-SUM(J$5:J7),IF(H8>'Inputs'!$B$9*'Inputs'!$B$5,MIN('Inputs'!$B$10*G8,'Inputs'!$B$8*'Inputs'!$B$5-SUM(J$5:J7)),0))) | K8: =MAX(0,MIN('Inputs'!$B$11*G8,'Inputs'!$B$12*'Inputs'!$B$5-SUM(K$5:K7))) | L8: =IF(A8='Inputs'!$B$7,SUM(K$5:K$53)/2,0)+IF(A8='Inputs'!$B$7+'Inputs'!$B$13,SUM(K$5:K$53)/2,0) | M8: =G8+I8-J8-K8+L8 | N8: =N7+M8
A9: 4 | B9: =EDATE('Inputs'!$B$6,A9) | C9: =IF(MONTH(B9)>='Inputs'!$B$15,YEAR(B9)&"/"&RIGHT(YEAR(B9)+1,2),(YEAR(B9)-1)&"/"&RIGHT(YEAR(B9),2)) | D9: =IF(A9>='Inputs'!$B$7,1,(1-COS(PI()*A9/'Inputs'!$B$7))/2) | E9: ='Inputs'!$B$5*(D9-D8) | F9: =SUMIF(Milestones!$D$5:$D$15,A9,Milestones!$E$5:$E$15) | G9: =IF('Inputs'!$B$14=1,E9,F9) | H9: =H8+G9 | I9: =IF(A9=0,'Inputs'!$B$8*'Inputs'!$B$5,0) | J9: =MAX(0,IF(A9='Inputs'!$B$7,'Inputs'!$B$8*'Inputs'!$B$5-SUM(J$5:J8),IF(H9>'Inputs'!$B$9*'Inputs'!$B$5,MIN('Inputs'!$B$10*G9,'Inputs'!$B$8*'Inputs'!$B$5-SUM(J$5:J8)),0))) | K9: =MAX(0,MIN('Inputs'!$B$11*G9,'Inputs'!$B$12*'Inputs'!$B$5-SUM(K$5:K8))) | L9: =IF(A9='Inputs'!$B$7,SUM(K$5:K$53)/2,0)+IF(A9='Inputs'!$B$7+'Inputs'!$B$13,SUM(K$5:K$53)/2,0) | M9: =G9+I9-J9-K9+L9 | N9: =N8+M9
A10: 5 | B10: =EDATE('Inputs'!$B$6,A10) | C10: =IF(MONTH(B10)>='Inputs'!$B$15,YEAR(B10)&"/"&RIGHT(YEAR(B10)+1,2),(YEAR(B10)-1)&"/"&RIGHT(YEAR(B10),2)) | D10: =IF(A10>='Inputs'!$B$7,1,(1-COS(PI()*A10/'Inputs'!$B$7))/2) | E10: ='Inputs'!$B$5*(D10-D9) | F10: =SUMIF(Milestones!$D$5:$D$15,A10,Milestones!$E$5:$E$15) | G10: =IF('Inputs'!$B$14=1,E10,F10) | H10: =H9+G10 | I10: =IF(A10=0,'Inputs'!$B$8*'Inputs'!$B$5,0) | J10: =MAX(0,IF(A10='Inputs'!$B$7,'Inputs'!$B$8*'Inputs'!$B$5-SUM(J$5:J9),IF(H10>'Inputs'!$B$9*'Inputs'!$B$5,MIN('Inputs'!$B$10*G10,'Inputs'!$B$8*'Inputs'!$B$5-SUM(J$5:J9)),0))) | K10: =MAX(0,MIN('Inputs'!$B$11*G10,'Inputs'!$B$12*'Inputs'!$B$5-SUM(K$5:K9))) | L10: =IF(A10='Inputs'!$B$7,SUM(K$5:K$53)/2,0)+IF(A10='Inputs'!$B$7+'Inputs'!$B$13,SUM(K$5:K$53)/2,0) | M10: =G10+I10-J10-K10+L10 | N10: =N9+M10
A11: 6 | B11: =EDATE('Inputs'!$B$6,A11) | C11: =IF(MONTH(B11)>='Inputs'!$B$15,YEAR(B11)&"/"&RIGHT(YEAR(B11)+1,2),(YEAR(B11)-1)&"/"&RIGHT(YEAR(B11),2)) | D11: =IF(A11>='Inputs'!$B$7,1,(1-COS(PI()*A11/'Inputs'!$B$7))/2) | E11: ='Inputs'!$B$5*(D11-D10) | F11: =SUMIF(Milestones!$D$5:$D$15,A11,Milestones!$E$5:$E$15) | G11: =IF('Inputs'!$B$14=1,E11,F11) | H11: =H10+G11 | I11: =IF(A11=0,'Inputs'!$B$8*'Inputs'!$B$5,0) | J11: =MAX(0,IF(A11='Inputs'!$B$7,'Inputs'!$B$8*'Inputs'!$B$5-SUM(J$5:J10),IF(H11>'Inputs'!$B$9*'Inputs'!$B$5,MIN('Inputs'!$B$10*G11,'Inputs'!$B$8*'Inputs'!$B$5-SUM(J$5:J10)),0))) | K11: =MAX(0,MIN('Inputs'!$B$11*G11,'Inputs'!$B$12*'Inputs'!$B$5-SUM(K$5:K10))) | L11: =IF(A11='Inputs'!$B$7,SUM(K$5:K$53)/2,0)+IF(A11='Inputs'!$B$7+'Inputs'!$B$13,SUM(K$5:K$53)/2,0) | M11: =G11+I11-J11-K11+L11 | N11: =N10+M11
A12: 7 | B12: =EDATE('Inputs'!$B$6,A12) | C12: =IF(MONTH(B12)>='Inputs'!$B$15,YEAR(B12)&"/"&RIGHT(YEAR(B12)+1,2),(YEAR(B12)-1)&"/"&RIGHT(YEAR(B12),2)) | D12: =IF(A12>='Inputs'!$B$7,1,(1-COS(PI()*A12/'Inputs'!$B$7))/2) | E12: ='Inputs'!$B$5*(D12-D11) | F12: =SUMIF(Milestones!$D$5:$D$15,A12,Milestones!$E$5:$E$15) | G12: =IF('Inputs'!$B$14=1,E12,F12) | H12: =H11+G12 | I12: =IF(A12=0,'Inputs'!$B$8*'Inputs'!$B$5,0) | J12: =MAX(0,IF(A12='Inputs'!$B$7,'Inputs'!$B$8*'Inputs'!$B$5-SUM(J$5:J11),IF(H12>'Inputs'!$B$9*'Inputs'!$B$5,MIN('Inputs'!$B$10*G12,'Inputs'!$B$8*'Inputs'!$B$5-SUM(J$5:J11)),0))) | K12: =MAX(0,MIN('Inputs'!$B$11*G12,'Inputs'!$B$12*'Inputs'!$B$5-SUM(K$5:K11))) | L12: =IF(A12='Inputs'!$B$7,SUM(K$5:K$53)/2,0)+IF(A12='Inputs'!$B$7+'Inputs'!$B$13,SUM(K$5:K$53)/2,0) | M12: =G12+I12-J12-K12+L12 | N12: =N11+M12
A13: 8 | B13: =EDATE('Inputs'!$B$6,A13) | C13: =IF(MONTH(B13)>='Inputs'!$B$15,YEAR(B13)&"/"&RIGHT(YEAR(B13)+1,2),(YEAR(B13)-1)&"/"&RIGHT(YEAR(B13),2)) | D13: =IF(A13>='Inputs'!$B$7,1,(1-COS(PI()*A13/'Inputs'!$B$7))/2) | E13: ='Inputs'!$B$5*(D13-D12) | F13: =SUMIF(Milestones!$D$5:$D$15,A13,Milestones!$E$5:$E$15) | G13: =IF('Inputs'!$B$14=1,E13,F13) | H13: =H12+G13 | I13: =IF(A13=0,'Inputs'!$B$8*'Inputs'!$B$5,0) | J13: =MAX(0,IF(A13='Inputs'!$B$7,'Inputs'!$B$8*'Inputs'!$B$5-SUM(J$5:J12),IF(H13>'Inputs'!$B$9*'Inputs'!$B$5,MIN('Inputs'!$B$10*G13,'Inputs'!$B$8*'Inputs'!$B$5-SUM(J$5:J12)),0))) | K13: =MAX(0,MIN('Inputs'!$B$11*G13,'Inputs'!$B$12*'Inputs'!$B$5-SUM(K$5:K12))) | L13: =IF(A13='Inputs'!$B$7,SUM(K$5:K$53)/2,0)+IF(A13='Inputs'!$B$7+'Inputs'!$B$13,SUM(K$5:K$53)/2,0) | M13: =G13+I13-J13-K13+L13 | N13: =N12+M13
A14: 9 | B14: =EDATE('Inputs'!$B$6,A14) | C14: =IF(MONTH(B14)>='Inputs'!$B$15,YEAR(B14)&"/"&RIGHT(YEAR(B14)+1,2),(YEAR(B14)-1)&"/"&RIGHT(YEAR(B14),2)) | D14: =IF(A14>='Inputs'!$B$7,1,(1-COS(PI()*A14/'Inputs'!$B$7))/2) | E14: ='Inputs'!$B$5*(D14-D13) | F14: =SUMIF(Milestones!$D$5:$D$15,A14,Milestones!$E$5:$E$15) | G14: =IF('Inputs'!$B$14=1,E14,F14) | H14: =H13+G14 | I14: =IF(A14=0,'Inputs'!$B$8*'Inputs'!$B$5,0) | J14: =MAX(0,IF(A14='Inputs'!$B$7,'Inputs'!$B$8*'Inputs'!$B$5-SUM(J$5:J13),IF(H14>'Inputs'!$B$9*'Inputs'!$B$5,MIN('Inputs'!$B$10*G14,'Inputs'!$B$8*'Inputs'!$B$5-SUM(J$5:J13)),0))) | K14: =MAX(0,MIN('Inputs'!$B$11*G14,'Inputs'!$B$12*'Inputs'!$B$5-SUM(K$5:K13))) | L14: =IF(A14='Inputs'!$B$7,SUM(K$5:K$53)/2,0)+IF(A14='Inputs'!$B$7+'Inputs'!$B$13,SUM(K$5:K$53)/2,0) | M14: =G14+I14-J14-K14+L14 | N14: =N13+M14
A15: 10 | B15: =EDATE('Inputs'!$B$6,A15) | C15: =IF(MONTH(B15)>='Inputs'!$B$15,YEAR(B15)&"/"&RIGHT(YEAR(B15)+1,2),(YEAR(B15)-1)&"/"&RIGHT(YEAR(B15),2)) | D15: =IF(A15>='Inputs'!$B$7,1,(1-COS(PI()*A15/'Inputs'!$B$7))/2) | E15: ='Inputs'!$B$5*(D15-D14) | F15: =SUMIF(Milestones!$D$5:$D$15,A15,Milestones!$E$5:$E$15) | G15: =IF('Inputs'!$B$14=1,E15,F15) | H15: =H14+G15 | I15: =IF(A15=0,'Inputs'!$B$8*'Inputs'!$B$5,0) | J15: =MAX(0,IF(A15='Inputs'!$B$7,'Inputs'!$B$8*'Inputs'!$B$5-SUM(J$5:J14),IF(H15>'Inputs'!$B$9*'Inputs'!$B$5,MIN('Inputs'!$B$10*G15,'Inputs'!$B$8*'Inputs'!$B$5-SUM(J$5:J14)),0))) | K15: =MAX(0,MIN('Inputs'!$B$11*G15,'Inputs'!$B$12*'Inputs'!$B$5-SUM(K$5:K14))) | L15: =IF(A15='Inputs'!$B$7,SUM(K$5:K$53)/2,0)+IF(A15='Inputs'!$B$7+'Inputs'!$B$13,SUM(K$5:K$53)/2,0) | M15: =G15+I15-J15-K15+L15 | N15: =N14+M15
A16: 11 | B16: =EDATE('Inputs'!$B$6,A16) | C16: =IF(MONTH(B16)>='Inputs'!$B$15,YEAR(B16)&"/"&RIGHT(YEAR(B16)+1,2),(YEAR(B16)-1)&"/"&RIGHT(YEAR(B16),2)) | D16: =IF(A16>='Inputs'!$B$7,1,(1-COS(PI()*A16/'Inputs'!$B$7))/2) | E16: ='Inputs'!$B$5*(D16-D15) | F16: =SUMIF(Milestones!$D$5:$D$15,A16,Milestones!$E$5:$E$15) | G16: =IF('Inputs'!$B$14=1,E16,F16) | H16: =H15+G16 | I16: =IF(A16=0,'Inputs'!$B$8*'Inputs'!$B$5,0) | J16: =MAX(0,IF(A16='Inputs'!$B$7,'Inputs'!$B$8*'Inputs'!$B$5-SUM(J$5:J15),IF(H16>'Inputs'!$B$9*'Inputs'!$B$5,MIN('Inputs'!$B$10*G16,'Inputs'!$B$8*'Inputs'!$B$5-SUM(J$5:J15)),0))) | K16: =MAX(0,MIN('Inputs'!$B$11*G16,'Inputs'!$B$12*'Inputs'!$B$5-SUM(K$5:K15))) | L16: =IF(A16='Inputs'!$B$7,SUM(K$5:K$53)/2,0)+IF(A16='Inputs'!$B$7+'Inputs'!$B$13,SUM(K$5:K$53)/2,0) | M16: =G16+I16-J16-K16+L16 | N16: =N15+M16
A17: 12 | B17: =EDATE('Inputs'!$B$6,A17) | C17: =IF(MONTH(B17)>='Inputs'!$B$15,YEAR(B17)&"/"&RIGHT(YEAR(B17)+1,2),(YEAR(B17)-1)&"/"&RIGHT(YEAR(B17),2)) | D17: =IF(A17>='Inputs'!$B$7,1,(1-COS(PI()*A17/'Inputs'!$B$7))/2) | E17: ='Inputs'!$B$5*(D17-D16) | F17: =SUMIF(Milestones!$D$5:$D$15,A17,Milestones!$E$5:$E$15) | G17: =IF('Inputs'!$B$14=1,E17,F17) | H17: =H16+G17 | I17: =IF(A17=0,'Inputs'!$B$8*'Inputs'!$B$5,0) | J17: =MAX(0,IF(A17='Inputs'!$B$7,'Inputs'!$B$8*'Inputs'!$B$5-SUM(J$5:J16),IF(H17>'Inputs'!$B$9*'Inputs'!$B$5,MIN('Inputs'!$B$10*G17,'Inputs'!$B$8*'Inputs'!$B$5-SUM(J$5:J16)),0))) | K17: =MAX(0,MIN('Inputs'!$B$11*G17,'Inputs'!$B$12*'Inputs'!$B$5-SUM(K$5:K16))) | L17: =IF(A17='Inputs'!$B$7,SUM(K$5:K$53)/2,0)+IF(A17='Inputs'!$B$7+'Inputs'!$B$13,SUM(K$5:K$53)/2,0) | M17: =G17+I17-J17-K17+L17 | N17: =N16+M17
... A53: 48 | B53: =EDATE('Inputs'!$B$6,A53) | C53: =IF(MONTH(B53)>='Inputs'!$B$15,YEAR(B53)&"/"&RIGHT(YEAR(B53)+1,2),(YEAR(B53)-1)&"/"&RIGHT(YEAR(B53),2)) | D53: =IF(A53>='Inputs'!$B$7,1,(1-COS(PI()*A53/'Inputs'!$B$7))/2) | E53: ='Inputs'!$B$5*(D53-D52) | F53: =SUMIF(Milestones!$D$5:$D$15,A53,Milestones!$E$5:$E$15) | G53: =IF('Inputs'!$B$14=1,E53,F53) | H53: =H52+G53 | I53: =IF(A53=0,'Inputs'!$B$8*'Inputs'!$B$5,0) | J53: =MAX(0,IF(A53='Inputs'!$B$7,'Inputs'!$B$8*'Inputs'!$B$5-SUM(J$5:J52),IF(H53>'Inputs'!$B$9*'Inputs'!$B$5,MIN('Inputs'!$B$10*G53,'Inputs'!$B$8*'Inputs'!$B$5-SUM(J$5:J52)),0))) | K53: =MAX(0,MIN('Inputs'!$B$11*G53,'Inputs'!$B$12*'Inputs'!$B$5-SUM(K$5:K52))) | L53: =IF(A53='Inputs'!$B$7,SUM(K$5:K$53)/2,0)+IF(A53='Inputs'!$B$7+'Inputs'!$B$13,SUM(K$5:K$53)/2,0) | M53: =G53+I53-J53-K53+L53 | N53: =N52+M53
A54: Total | G54: =SUM(G5:G53) | I54: =SUM(I5:I53) | J54: =SUM(J5:J53) | K54: =SUM(K5:K53) | L54: =SUM(L5:L53) | M54: =SUM(M5:M53)

Sheet FY Budget
A1: Fiscal-year budget request (KWD m)
A2: SUMIF of the monthly forecast by fiscal-year label.
A4: Fiscal year | B4: Gross work certified | C4: Advance paid | D4: Advance recovered | E4: Retention held | F4: Retention released | G4: Net cash payment (budget need) | H4: Cumulative net
A5: =(YEAR('Inputs'!$B$6)-IF(MONTH('Inputs'!$B$6)<'Inputs'!$B$15,1,0)+0)&"/"&RIGHT((YEAR('Inputs'!$B$6)-IF(MONTH('Inputs'!$B$6)<'Inputs'!$B$15,1,0)+0)+1,2) | B5: =SUMIF(Monthly!$C$5:$C$53,$A5,Monthly!$G$5:$G$53) | C5: =SUMIF(Monthly!$C$5:$C$53,$A5,Monthly!$I$5:$I$53) | D5: =SUMIF(Monthly!$C$5:$C$53,$A5,Monthly!$J$5:$J$53) | E5: =SUMIF(Monthly!$C$5:$C$53,$A5,Monthly!$K$5:$K$53) | F5: =SUMIF(Monthly!$C$5:$C$53,$A5,Monthly!$L$5:$L$53) | G5: =SUMIF(Monthly!$C$5:$C$53,$A5,Monthly!$M$5:$M$53) | H5: =G5
A6: =(YEAR('Inputs'!$B$6)-IF(MONTH('Inputs'!$B$6)<'Inputs'!$B$15,1,0)+1)&"/"&RIGHT((YEAR('Inputs'!$B$6)-IF(MONTH('Inputs'!$B$6)<'Inputs'!$B$15,1,0)+1)+1,2) | B6: =SUMIF(Monthly!$C$5:$C$53,$A6,Monthly!$G$5:$G$53) | C6: =SUMIF(Monthly!$C$5:$C$53,$A6,Monthly!$I$5:$I$53) | D6: =SUMIF(Monthly!$C$5:$C$53,$A6,Monthly!$J$5:$J$53) | E6: =SUMIF(Monthly!$C$5:$C$53,$A6,Monthly!$K$5:$K$53) | F6: =SUMIF(Monthly!$C$5:$C$53,$A6,Monthly!$L$5:$L$53) | G6: =SUMIF(Monthly!$C$5:$C$53,$A6,Monthly!$M$5:$M$53) | H6: =H5+G6
A7: =(YEAR('Inputs'!$B$6)-IF(MONTH('Inputs'!$B$6)<'Inputs'!$B$15,1,0)+2)&"/"&RIGHT((YEAR('Inputs'!$B$6)-IF(MONTH('Inputs'!$B$6)<'Inputs'!$B$15,1,0)+2)+1,2) | B7: =SUMIF(Monthly!$C$5:$C$53,$A7,Monthly!$G$5:$G$53) | C7: =SUMIF(Monthly!$C$5:$C$53,$A7,Monthly!$I$5:$I$53) | D7: =SUMIF(Monthly!$C$5:$C$53,$A7,Monthly!$J$5:$J$53) | E7: =SUMIF(Monthly!$C$5:$C$53,$A7,Monthly!$K$5:$K$53) | F7: =SUMIF(Monthly!$C$5:$C$53,$A7,Monthly!$L$5:$L$53) | G7: =SUMIF(Monthly!$C$5:$C$53,$A7,Monthly!$M$5:$M$53) | H7: =H6+G7
A8: =(YEAR('Inputs'!$B$6)-IF(MONTH('Inputs'!$B$6)<'Inputs'!$B$15,1,0)+3)&"/"&RIGHT((YEAR('Inputs'!$B$6)-IF(MONTH('Inputs'!$B$6)<'Inputs'!$B$15,1,0)+3)+1,2) | B8: =SUMIF(Monthly!$C$5:$C$53,$A8,Monthly!$G$5:$G$53) | C8: =SUMIF(Monthly!$C$5:$C$53,$A8,Monthly!$I$5:$I$53) | D8: =SUMIF(Monthly!$C$5:$C$53,$A8,Monthly!$J$5:$J$53) | E8: =SUMIF(Monthly!$C$5:$C$53,$A8,Monthly!$K$5:$K$53) | F8: =SUMIF(Monthly!$C$5:$C$53,$A8,Monthly!$L$5:$L$53) | G8: =SUMIF(Monthly!$C$5:$C$53,$A8,Monthly!$M$5:$M$53) | H8: =H7+G8
A9: =(YEAR('Inputs'!$B$6)-IF(MONTH('Inputs'!$B$6)<'Inputs'!$B$15,1,0)+4)&"/"&RIGHT((YEAR('Inputs'!$B$6)-IF(MONTH('Inputs'!$B$6)<'Inputs'!$B$15,1,0)+4)+1,2) | B9: =SUMIF(Monthly!$C$5:$C$53,$A9,Monthly!$G$5:$G$53) | C9: =SUMIF(Monthly!$C$5:$C$53,$A9,Monthly!$I$5:$I$53) | D9: =SUMIF(Monthly!$C$5:$C$53,$A9,Monthly!$J$5:$J$53) | E9: =SUMIF(Monthly!$C$5:$C$53,$A9,Monthly!$K$5:$K$53) | F9: =SUMIF(Monthly!$C$5:$C$53,$A9,Monthly!$L$5:$L$53) | G9: =SUMIF(Monthly!$C$5:$C$53,$A9,Monthly!$M$5:$M$53) | H9: =H8+G9
A11: Check: total net = contract amount | G11: =SUM(G5:G9)-'Inputs'!$B$5

Sheet Contingency
A1: Budget, commitment and contingency drawdown (KWD m)
A2: Commitment = contract value + approved variations; expenditure = cash paid.
A4: Input | B4: Value | C4: Unit | D4: Note / typical range
A5: Project contingency in approved budget | B5: 4.5 | C5: KWD m | D5: 10% of contract; sized from the risk register (P80)
A6: Owner's costs (consultant supervision, permits, MEWRE staff) | B6: 2 | C6: KWD m
A9: Change / risk item | B9: Status | C9: Value | D9: Probability | E9: Expected value | F9: Draws contingency?
A10: VO-01 Additional tower foundation design for sabkha soil | B10: Approved | C10: 0.95 | D10: 1 | E10: =C10*D10 | F10: =IF(B10="Approved","Drawn","Forecast")
A11: VO-02 Extra 400 kV bay protection panel requested by MEWRE Transmission | B11: Approved | C11: 0.65 | D11: 1 | E11: =C11*D11 | F11: =IF(B11="Approved","Drawn","Forecast")
A12: Claim-01 Late site access (land handover by Employer) | B12: Pending | C12: 1.6 | D12: 0.5 | E12: =C12*D12 | F12: =IF(B12="Approved","Drawn","Forecast")
A13: Claim-02 Change in customs procedure (contractor claim) | B13: Pending | C13: 0.8 | D13: 0.5 | E13: =C13*D13 | F13: =IF(B13="Approved","Drawn","Forecast")
A14: Risk R-07 Outage window slippage on existing Al-Wafra substation | B14: Risk (P80 allowance) | C14: 2 | D14: 0.4 | E14: =C14*D14 | F14: =IF(B14="Approved","Drawn","Forecast")
A15: (add item) | E15: =IF(C15="",0,C15*D15) | F15: =IF(B15="Approved","Drawn",IF(B15="","","Forecast"))
A16: (add item) | E16: =IF(C16="",0,C16*D16) | F16: =IF(B16="Approved","Drawn",IF(B16="","","Forecast"))
A17: (add item) | E17: =IF(C17="",0,C17*D17) | F17: =IF(B17="Approved","Drawn",IF(B17="","","Forecast"))
A19: Budget position | B19: Value | C19: Unit | D19: How it is calculated
A20: Approved budget = contract + contingency + owner's costs | B20: ='Inputs'!$B$5+'Contingency'!$B$5+'Contingency'!$B$6 | C20: KWD m
A21: Contingency drawn (approved variations) | B21: =SUMIF(B10:B17,"Approved",C10:C17) | C21: KWD m
A22: Commitment = contract + approved variations | B22: ='Inputs'!$B$5+B21 | C22: KWD m
A23: Contingency remaining | B23: ='Contingency'!$B$5-B21 | C23: KWD m
A24: Expected value of pending claims and risks | B24: =SUMPRODUCT((B10:B17<>"Approved")*(B10:B17<>"")*E10:E17) | C24: KWD m
A25: Contingency surplus (+) / shortfall (-) | B25: =B23-B24 | C25: KWD m | D25: Negative = prepare a budget-increase justification
A26: Forecast final cost (EAC) of the package | B26: =B22+B24+'Contingency'!$B$6 | C26: KWD m
