Workbook

Sheet README
A1: Earned value tracker — monthly (Module 10, Lesson 6; Module 8 EVM)
A3: Yellow cells with blue bold text = INPUTS you may change.
A4: Green cells = key RESULTS (formulas — do not overwrite).
A6: WHAT THIS MODEL DOES
A7: Tracks a contract or programme budget monthly with earned value management: PV (planned value), EV (earned value) and AC (actual cost) cumulative, and computes CV, SV, CPI, SPI, three EAC methods, ETC, VAC and TCPI. Example: a KWD 45.0 m grid-connection EPC package, 24 months, status at month 12.
A8: Sheets: Inputs (BAC, status month) -> Monthly (enter planned % and cumulative EV and AC each month) -> Status (dashboard at the status month) -> Guidance.
A9: Owner-side caution: on a lump-sum FIDIC contract MEWRE's cost is the Contract Price plus variations and claims, not the contractor's internal cost. Use AC = amounts certified (or accrued) for the Employer's view, and keep a separate forecast of variations and claims (see cashflow-forecast.xlsx, Contingency sheet).
A10: EXERCISES
A11: 1. Read the Status sheet at month 12: CPI 0.934, SPI 0.880. Which EAC method would you report to the Undersecretary, and why?
A12: 2. Change the status month to 9. How have CPI and SPI trended? Is the trend or the point value more informative?
A13: 3. Enter your own EV and AC for months 13–15 assuming the contractor recovers (CPI 0.95, SPI 0.95). Recompute TCPI.
A14: 4. Plot PV, EV and AC (Insert > Line chart on Monthly columns C, E, F) and annotate CV and SV at the status date.
... A17: Currency convention: USD for IPP economics, KWD for ministry budgets; assumed 1 KWD = 3.25 USD (change in Inputs where shown).

Sheet Inputs
A1: Inputs — EVM tracker
A4: Input | B4: Value | C4: Unit | D4: Note / typical range
A5: Budget at completion (BAC) | B5: 45 | C5: KWD m
A6: Status month | B6: 12 | C6: month no. | D6: 1–24
A7: Planned duration | B7: 24 | C7: months

Sheet Monthly
A1: Monthly EVM table
A2: Enter planned cumulative %, EV cumulative and AC cumulative (yellow). Leave EV/AC blank for future months.
A4: Month | B4: Planned cum. % | C4: PV cum. (KWD m) | D4: EV cum. % complete | E4: EV cum. (KWD m) | F4: AC cum. (KWD m) | G4: CV = EV-AC | H4: SV = EV-PV | I4: CPI = EV/AC | J4: SPI = EV/PV | K4: EAC1 = BAC/CPI | L4: EAC2 = AC+(BAC-EV) | M4: EAC3 = AC+(BAC-EV)/(CPI*SPI) | N4: ETC = EAC1-AC | O4: VAC = BAC-EAC1 | P4: TCPI = (BAC-EV)/(BAC-AC)
A5: 1 | B5: 0.0043 | C5: =B5*'Inputs'!$B$5 | D5: =IF(E5="","",E5/'Inputs'!$B$5) | E5: 0.191 | F5: 0.192 | G5: =IF(E5="","",E5-F5) | H5: =IF(E5="","",E5-C5) | I5: =IF(E5="","",E5/F5) | J5: =IF(E5="","",E5/C5) | K5: =IF(E5="","",'Inputs'!$B$5/I5) | L5: =IF(E5="","",F5+'Inputs'!$B$5-E5) | M5: =IF(E5="","",F5+('Inputs'!$B$5-E5)/(I5*J5)) | N5: =IF(E5="","",K5-F5) | O5: =IF(E5="","",'Inputs'!$B$5-K5) | P5: =IF(E5="","",('Inputs'!$B$5-E5)/('Inputs'!$B$5-F5))
A6: 2 | B6: 0.017 | C6: =B6*'Inputs'!$B$5 | D6: =IF(E6="","",E6/'Inputs'!$B$5) | E6: 0.751 | F6: 0.759 | G6: =IF(E6="","",E6-F6) | H6: =IF(E6="","",E6-C6) | I6: =IF(E6="","",E6/F6) | J6: =IF(E6="","",E6/C6) | K6: =IF(E6="","",'Inputs'!$B$5/I6) | L6: =IF(E6="","",F6+'Inputs'!$B$5-E6) | M6: =IF(E6="","",F6+('Inputs'!$B$5-E6)/(I6*J6)) | N6: =IF(E6="","",K6-F6) | O6: =IF(E6="","",'Inputs'!$B$5-K6) | P6: =IF(E6="","",('Inputs'!$B$5-E6)/('Inputs'!$B$5-F6))
A7: 3 | B7: 0.0381 | C7: =B7*'Inputs'!$B$5 | D7: =IF(E7="","",E7/'Inputs'!$B$5) | E7: 1.661 | F7: 1.689 | G7: =IF(E7="","",E7-F7) | H7: =IF(E7="","",E7-C7) | I7: =IF(E7="","",E7/F7) | J7: =IF(E7="","",E7/C7) | K7: =IF(E7="","",'Inputs'!$B$5/I7) | L7: =IF(E7="","",F7+'Inputs'!$B$5-E7) | M7: =IF(E7="","",F7+('Inputs'!$B$5-E7)/(I7*J7)) | N7: =IF(E7="","",K7-F7) | O7: =IF(E7="","",'Inputs'!$B$5-K7) | P7: =IF(E7="","",('Inputs'!$B$5-E7)/('Inputs'!$B$5-F7))
A8: 4 | B8: 0.067 | C8: =B8*'Inputs'!$B$5 | D8: =IF(E8="","",E8/'Inputs'!$B$5) | E8: 2.894 | F8: 2.959 | G8: =IF(E8="","",E8-F8) | H8: =IF(E8="","",E8-C8) | I8: =IF(E8="","",E8/F8) | J8: =IF(E8="","",E8/C8) | K8: =IF(E8="","",'Inputs'!$B$5/I8) | L8: =IF(E8="","",F8+'Inputs'!$B$5-E8) | M8: =IF(E8="","",F8+('Inputs'!$B$5-E8)/(I8*J8)) | N8: =IF(E8="","",K8-F8) | O8: =IF(E8="","",'Inputs'!$B$5-K8) | P8: =IF(E8="","",('Inputs'!$B$5-E8)/('Inputs'!$B$5-F8))
A9: 5 | B9: 0.1033 | C9: =B9*'Inputs'!$B$5 | D9: =IF(E9="","",E9/'Inputs'!$B$5) | E9: 4.417 | F9: 4.542 | G9: =IF(E9="","",E9-F9) | H9: =IF(E9="","",E9-C9) | I9: =IF(E9="","",E9/F9) | J9: =IF(E9="","",E9/C9) | K9: =IF(E9="","",'Inputs'!$B$5/I9) | L9: =IF(E9="","",F9+'Inputs'!$B$5-E9) | M9: =IF(E9="","",F9+('Inputs'!$B$5-E9)/(I9*J9)) | N9: =IF(E9="","",K9-F9) | O9: =IF(E9="","",'Inputs'!$B$5-K9) | P9: =IF(E9="","",('Inputs'!$B$5-E9)/('Inputs'!$B$5-F9))
A10: 6 | B10: 0.1464 | C10: =B10*'Inputs'!$B$5 | D10: =IF(E10="","",E10/'Inputs'!$B$5) | E10: 6.195 | F10: 6.407 | G10: =IF(E10="","",E10-F10) | H10: =IF(E10="","",E10-C10) | I10: =IF(E10="","",E10/F10) | J10: =IF(E10="","",E10/C10) | K10: =IF(E10="","",'Inputs'!$B$5/I10) | L10: =IF(E10="","",F10+'Inputs'!$B$5-E10) | M10: =IF(E10="","",F10+('Inputs'!$B$5-E10)/(I10*J10)) | N10: =IF(E10="","",K10-F10) | O10: =IF(E10="","",'Inputs'!$B$5-K10) | P10: =IF(E10="","",('Inputs'!$B$5-E10)/('Inputs'!$B$5-F10))
A11: 7 | B11: 0.1956 | C11: =B11*'Inputs'!$B$5 | D11: =IF(E11="","",E11/'Inputs'!$B$5) | E11: 8.187 | F11: 8.515 | G11: =IF(E11="","",E11-F11) | H11: =IF(E11="","",E11-C11) | I11: =IF(E11="","",E11/F11) | J11: =IF(E11="","",E11/C11) | K11: =IF(E11="","",'Inputs'!$B$5/I11) | L11: =IF(E11="","",F11+'Inputs'!$B$5-E11) | M11: =IF(E11="","",F11+('Inputs'!$B$5-E11)/(I11*J11)) | N11: =IF(E11="","",K11-F11) | O11: =IF(E11="","",'Inputs'!$B$5-K11) | P11: =IF(E11="","",('Inputs'!$B$5-E11)/('Inputs'!$B$5-F11))
A12: 8 | B12: 0.25 | C12: =B12*'Inputs'!$B$5 | D12: =IF(E12="","",E12/'Inputs'!$B$5) | E12: 10.35 | F12: 10.827 | G12: =IF(E12="","",E12-F12) | H12: =IF(E12="","",E12-C12) | I12: =IF(E12="","",E12/F12) | J12: =IF(E12="","",E12/C12) | K12: =IF(E12="","",'Inputs'!$B$5/I12) | L12: =IF(E12="","",F12+'Inputs'!$B$5-E12) | M12: =IF(E12="","",F12+('Inputs'!$B$5-E12)/(I12*J12)) | N12: =IF(E12="","",K12-F12) | O12: =IF(E12="","",'Inputs'!$B$5-K12) | P12: =IF(E12="","",('Inputs'!$B$5-E12)/('Inputs'!$B$5-F12))
A13: 9 | B13: 0.3087 | C13: =B13*'Inputs'!$B$5 | D13: =IF(E13="","",E13/'Inputs'!$B$5) | E13: 12.64 | F13: 13.299 | G13: =IF(E13="","",E13-F13) | H13: =IF(E13="","",E13-C13) | I13: =IF(E13="","",E13/F13) | J13: =IF(E13="","",E13/C13) | K13: =IF(E13="","",'Inputs'!$B$5/I13) | L13: =IF(E13="","",F13+'Inputs'!$B$5-E13) | M13: =IF(E13="","",F13+('Inputs'!$B$5-E13)/(I13*J13)) | N13: =IF(E13="","",K13-F13) | O13: =IF(E13="","",'Inputs'!$B$5-K13) | P13: =IF(E13="","",('Inputs'!$B$5-E13)/('Inputs'!$B$5-F13))
A14: 10 | B14: 0.3706 | C14: =B14*'Inputs'!$B$5 | D14: =IF(E14="","",E14/'Inputs'!$B$5) | E14: 15.009 | F14: 15.883 | G14: =IF(E14="","",E14-F14) | H14: =IF(E14="","",E14-C14) | I14: =IF(E14="","",E14/F14) | J14: =IF(E14="","",E14/C14) | K14: =IF(E14="","",'Inputs'!$B$5/I14) | L14: =IF(E14="","",F14+'Inputs'!$B$5-E14) | M14: =IF(E14="","",F14+('Inputs'!$B$5-E14)/(I14*J14)) | N14: =IF(E14="","",K14-F14) | O14: =IF(E14="","",'Inputs'!$B$5-K14) | P14: =IF(E14="","",('Inputs'!$B$5-E14)/('Inputs'!$B$5-F14))
A15: 11 | B15: 0.4347 | C15: =B15*'Inputs'!$B$5 | D15: =IF(E15="","",E15/'Inputs'!$B$5) | E15: 17.411 | F15: 18.533 | G15: =IF(E15="","",E15-F15) | H15: =IF(E15="","",E15-C15) | I15: =IF(E15="","",E15/F15) | J15: =IF(E15="","",E15/C15) | K15: =IF(E15="","",'Inputs'!$B$5/I15) | L15: =IF(E15="","",F15+'Inputs'!$B$5-E15) | M15: =IF(E15="","",F15+('Inputs'!$B$5-E15)/(I15*J15)) | N15: =IF(E15="","",K15-F15) | O15: =IF(E15="","",'Inputs'!$B$5-K15) | P15: =IF(E15="","",('Inputs'!$B$5-E15)/('Inputs'!$B$5-F15))
A16: 12 | B16: 0.5 | C16: =B16*'Inputs'!$B$5 | D16: =IF(E16="","",E16/'Inputs'!$B$5) | E16: 19.8 | F16: 21.2 | G16: =IF(E16="","",E16-F16) | H16: =IF(E16="","",E16-C16) | I16: =IF(E16="","",E16/F16) | J16: =IF(E16="","",E16/C16) | K16: =IF(E16="","",'Inputs'!$B$5/I16) | L16: =IF(E16="","",F16+'Inputs'!$B$5-E16) | M16: =IF(E16="","",F16+('Inputs'!$B$5-E16)/(I16*J16)) | N16: =IF(E16="","",K16-F16) | O16: =IF(E16="","",'Inputs'!$B$5-K16) | P16: =IF(E16="","",('Inputs'!$B$5-E16)/('Inputs'!$B$5-F16))
A17: 13 | B17: 0.5653 | C17: =B17*'Inputs'!$B$5 | D17: =IF(E17="","",E17/'Inputs'!$B$5) | G17: =IF(E17="","",E17-F17) | H17: =IF(E17="","",E17-C17) | I17: =IF(E17="","",E17/F17) | J17: =IF(E17="","",E17/C17) | K17: =IF(E17="","",'Inputs'!$B$5/I17) | L17: =IF(E17="","",F17+'Inputs'!$B$5-E17) | M17: =IF(E17="","",F17+('Inputs'!$B$5-E17)/(I17*J17)) | N17: =IF(E17="","",K17-F17) | O17: =IF(E17="","",'Inputs'!$B$5-K17) | P17: =IF(E17="","",('Inputs'!$B$5-E17)/('Inputs'!$B$5-F17))
A18: 14 | B18: 0.6294 | C18: =B18*'Inputs'!$B$5 | D18: =IF(E18="","",E18/'Inputs'!$B$5) | G18: =IF(E18="","",E18-F18) | H18: =IF(E18="","",E18-C18) | I18: =IF(E18="","",E18/F18) | J18: =IF(E18="","",E18/C18) | K18: =IF(E18="","",'Inputs'!$B$5/I18) | L18: =IF(E18="","",F18+'Inputs'!$B$5-E18) | M18: =IF(E18="","",F18+('Inputs'!$B$5-E18)/(I18*J18)) | N18: =IF(E18="","",K18-F18) | O18: =IF(E18="","",'Inputs'!$B$5-K18) | P18: =IF(E18="","",('Inputs'!$B$5-E18)/('Inputs'!$B$5-F18))
A19: 15 | B19: 0.6913 | C19: =B19*'Inputs'!$B$5 | D19: =IF(E19="","",E19/'Inputs'!$B$5) | G19: =IF(E19="","",E19-F19) | H19: =IF(E19="","",E19-C19) | I19: =IF(E19="","",E19/F19) | J19: =IF(E19="","",E19/C19) | K19: =IF(E19="","",'Inputs'!$B$5/I19) | L19: =IF(E19="","",F19+'Inputs'!$B$5-E19) | M19: =IF(E19="","",F19+('Inputs'!$B$5-E19)/(I19*J19)) | N19: =IF(E19="","",K19-F19) | O19: =IF(E19="","",'Inputs'!$B$5-K19) | P19: =IF(E19="","",('Inputs'!$B$5-E19)/('Inputs'!$B$5-F19))
A20: 16 | B20: 0.75 | C20: =B20*'Inputs'!$B$5 | D20: =IF(E20="","",E20/'Inputs'!$B$5) | G20: =IF(E20="","",E20-F20) | H20: =IF(E20="","",E20-C20) | I20: =IF(E20="","",E20/F20) | J20: =IF(E20="","",E20/C20) | K20: =IF(E20="","",'Inputs'!$B$5/I20) | L20: =IF(E20="","",F20+'Inputs'!$B$5-E20) | M20: =IF(E20="","",F20+('Inputs'!$B$5-E20)/(I20*J20)) | N20: =IF(E20="","",K20-F20) | O20: =IF(E20="","",'Inputs'!$B$5-K20) | P20: =IF(E20="","",('Inputs'!$B$5-E20)/('Inputs'!$B$5-F20))
A21: 17 | B21: 0.8044 | C21: =B21*'Inputs'!$B$5 | D21: =IF(E21="","",E21/'Inputs'!$B$5) | G21: =IF(E21="","",E21-F21) | H21: =IF(E21="","",E21-C21) | I21: =IF(E21="","",E21/F21) | J21: =IF(E21="","",E21/C21) | K21: =IF(E21="","",'Inputs'!$B$5/I21) | L21: =IF(E21="","",F21+'Inputs'!$B$5-E21) | M21: =IF(E21="","",F21+('Inputs'!$B$5-E21)/(I21*J21)) | N21: =IF(E21="","",K21-F21) | O21: =IF(E21="","",'Inputs'!$B$5-K21) | P21: =IF(E21="","",('Inputs'!$B$5-E21)/('Inputs'!$B$5-F21))
A22: 18 | B22: 0.8536 | C22: =B22*'Inputs'!$B$5 | D22: =IF(E22="","",E22/'Inputs'!$B$5) | G22: =IF(E22="","",E22-F22) | H22: =IF(E22="","",E22-C22) | I22: =IF(E22="","",E22/F22) | J22: =IF(E22="","",E22/C22) | K22: =IF(E22="","",'Inputs'!$B$5/I22) | L22: =IF(E22="","",F22+'Inputs'!$B$5-E22) | M22: =IF(E22="","",F22+('Inputs'!$B$5-E22)/(I22*J22)) | N22: =IF(E22="","",K22-F22) | O22: =IF(E22="","",'Inputs'!$B$5-K22) | P22: =IF(E22="","",('Inputs'!$B$5-E22)/('Inputs'!$B$5-F22))
A23: 19 | B23: 0.8967 | C23: =B23*'Inputs'!$B$5 | D23: =IF(E23="","",E23/'Inputs'!$B$5) | G23: =IF(E23="","",E23-F23) | H23: =IF(E23="","",E23-C23) | I23: =IF(E23="","",E23/F23) | J23: =IF(E23="","",E23/C23) | K23: =IF(E23="","",'Inputs'!$B$5/I23) | L23: =IF(E23="","",F23+'Inputs'!$B$5-E23) | M23: =IF(E23="","",F23+('Inputs'!$B$5-E23)/(I23*J23)) | N23: =IF(E23="","",K23-F23) | O23: =IF(E23="","",'Inputs'!$B$5-K23) | P23: =IF(E23="","",('Inputs'!$B$5-E23)/('Inputs'!$B$5-F23))
A24: 20 | B24: 0.933 | C24: =B24*'Inputs'!$B$5 | D24: =IF(E24="","",E24/'Inputs'!$B$5) | G24: =IF(E24="","",E24-F24) | H24: =IF(E24="","",E24-C24) | I24: =IF(E24="","",E24/F24) | J24: =IF(E24="","",E24/C24) | K24: =IF(E24="","",'Inputs'!$B$5/I24) | L24: =IF(E24="","",F24+'Inputs'!$B$5-E24) | M24: =IF(E24="","",F24+('Inputs'!$B$5-E24)/(I24*J24)) | N24: =IF(E24="","",K24-F24) | O24: =IF(E24="","",'Inputs'!$B$5-K24) | P24: =IF(E24="","",('Inputs'!$B$5-E24)/('Inputs'!$B$5-F24))
A25: 21 | B25: 0.9619 | C25: =B25*'Inputs'!$B$5 | D25: =IF(E25="","",E25/'Inputs'!$B$5) | G25: =IF(E25="","",E25-F25) | H25: =IF(E25="","",E25-C25) | I25: =IF(E25="","",E25/F25) | J25: =IF(E25="","",E25/C25) | K25: =IF(E25="","",'Inputs'!$B$5/I25) | L25: =IF(E25="","",F25+'Inputs'!$B$5-E25) | M25: =IF(E25="","",F25+('Inputs'!$B$5-E25)/(I25*J25)) | N25: =IF(E25="","",K25-F25) | O25: =IF(E25="","",'Inputs'!$B$5-K25) | P25: =IF(E25="","",('Inputs'!$B$5-E25)/('Inputs'!$B$5-F25))
A26: 22 | B26: 0.983 | C26: =B26*'Inputs'!$B$5 | D26: =IF(E26="","",E26/'Inputs'!$B$5) | G26: =IF(E26="","",E26-F26) | H26: =IF(E26="","",E26-C26) | I26: =IF(E26="","",E26/F26) | J26: =IF(E26="","",E26/C26) | K26: =IF(E26="","",'Inputs'!$B$5/I26) | L26: =IF(E26="","",F26+'Inputs'!$B$5-E26) | M26: =IF(E26="","",F26+('Inputs'!$B$5-E26)/(I26*J26)) | N26: =IF(E26="","",K26-F26) | O26: =IF(E26="","",'Inputs'!$B$5-K26) | P26: =IF(E26="","",('Inputs'!$B$5-E26)/('Inputs'!$B$5-F26))
A27: 23 | B27: 0.9957 | C27: =B27*'Inputs'!$B$5 | D27: =IF(E27="","",E27/'Inputs'!$B$5) | G27: =IF(E27="","",E27-F27) | H27: =IF(E27="","",E27-C27) | I27: =IF(E27="","",E27/F27) | J27: =IF(E27="","",E27/C27) | K27: =IF(E27="","",'Inputs'!$B$5/I27) | L27: =IF(E27="","",F27+'Inputs'!$B$5-E27) | M27: =IF(E27="","",F27+('Inputs'!$B$5-E27)/(I27*J27)) | N27: =IF(E27="","",K27-F27) | O27: =IF(E27="","",'Inputs'!$B$5-K27) | P27: =IF(E27="","",('Inputs'!$B$5-E27)/('Inputs'!$B$5-F27))
A28: 24 | B28: 1 | C28: =B28*'Inputs'!$B$5 | D28: =IF(E28="","",E28/'Inputs'!$B$5) | G28: =IF(E28="","",E28-F28) | H28: =IF(E28="","",E28-C28) | I28: =IF(E28="","",E28/F28) | J28: =IF(E28="","",E28/C28) | K28: =IF(E28="","",'Inputs'!$B$5/I28) | L28: =IF(E28="","",F28+'Inputs'!$B$5-E28) | M28: =IF(E28="","",F28+('Inputs'!$B$5-E28)/(I28*J28)) | N28: =IF(E28="","",K28-F28) | O28: =IF(E28="","",'Inputs'!$B$5-K28) | P28: =IF(E28="","",('Inputs'!$B$5-E28)/('Inputs'!$B$5-F28))

Sheet Status
A1: Status at the selected month
A4: Indicator | B4: Value | C4: Unit | D4: How it is calculated
A5: PV (planned value, cumulative) | B5: =INDEX(Monthly!$C$5:$C$28,'Inputs'!$B$6) | C5: KWD m
A6: EV (earned value, cumulative) | B6: =INDEX(Monthly!$E$5:$E$28,'Inputs'!$B$6) | C6: KWD m
A7: AC (actual cost, cumulative) | B7: =INDEX(Monthly!$F$5:$F$28,'Inputs'!$B$6) | C7: KWD m
A8: Cost variance CV | B8: =INDEX(Monthly!$G$5:$G$28,'Inputs'!$B$6) | C8: KWD m | D8: Negative = over cost for the work done
A9: Schedule variance SV | B9: =INDEX(Monthly!$H$5:$H$28,'Inputs'!$B$6) | C9: KWD m | D9: Negative = behind plan (in money terms)
A10: CPI | B10: =INDEX(Monthly!$I$5:$I$28,'Inputs'!$B$6) | C10: – | D10: <0.95 sustained = escalate
A11: SPI | B11: =INDEX(Monthly!$J$5:$J$28,'Inputs'!$B$6) | C11: – | D11: SPI tends to 1.0 at the end even if late — use time-based SPI(t) or the CPM schedule as well
A12: EAC1 = BAC/CPI (typical) | B12: =INDEX(Monthly!$K$5:$K$28,'Inputs'!$B$6) | C12: KWD m
A13: EAC2 = AC + (BAC-EV) (atypical, one-off) | B13: =INDEX(Monthly!$L$5:$L$28,'Inputs'!$B$6) | C13: KWD m
A14: EAC3 = AC + (BAC-EV)/(CPI x SPI) (schedule pressure) | B14: =INDEX(Monthly!$M$5:$M$28,'Inputs'!$B$6) | C14: KWD m
A15: TCPI (to complete within BAC) | B15: =INDEX(Monthly!$P$5:$P$28,'Inputs'!$B$6) | C15: – | D15: >1.10 is rarely achieved in practice
A16: Flag | B16: =IF(AND(B10<0.95,B11<0.95),"RED: cost and schedule",IF(OR(B10<0.95,B11<0.95),"AMBER","GREEN"))

Sheet Guidance
A1: GUIDANCE — reading EVM on a ministry project
A2: 1. PV comes from the baseline programme (resource-loaded P6 schedule or the payment S-curve). Freeze it at contract award; re-baseline only through formal change control.
A3: 2. EV must be measured, not estimated: use measured quantities x BoQ rates (remeasured contracts) or the agreed milestone/progress-weighting system (lump sum). Weighting rules belong in the contract's progress measurement procedure.
A4: 3. AC for the Employer = certified IPC value (plus owner's costs if tracking a programme). For a contractor, AC = its own cost; never mix the two bases in one CPI.
A5: 4. CPI < 0.95 or SPI < 0.95 for two consecutive months: ask for a recovery plan and update the cash-flow forecast and the budget request.
A6: 5. EAC choice: BAC/CPI when the cause is systemic (productivity, rates); AC + (BAC-EV) when the overrun was a one-off (e.g. a single repaired foundation); CPI x SPI when the client is forcing acceleration.
A7: 6. Report EAC with a range (best / most likely / worst) and connect it to contingency remaining. A single number invites false confidence.
