Workbook

Sheet README
A1: LCOE model — utility-scale PV (Module 10, Lesson 2)
A3: Yellow cells with blue bold text = INPUTS you may change.
A4: Green cells = key RESULTS (formulas — do not overwrite).
A6: WHAT THIS MODEL DOES
A7: Computes the levelized cost of electricity (LCOE) from first principles: the constant price per kWh whose present value of revenue equals the present value of all costs, NPV(costs) = NPV(energy x LCOE). It therefore solves LCOE = sum[(Capex_t + Opex_t)/(1+r)^t] / sum[E_t/(1+r)^t].
A8: Sheets: Inputs (all assumptions, shaded) -> Calc (annual rows, years 0-40, life switch) -> Results (LCOE in USD/MWh, US cents/kWh and fils/kWh, plus the capital-recovery-factor shortcut) -> Sensitivity (LCOE vs WACC table and a tornado table).
A9: Energy discounting: energy is discounted at the same rate as money. This is not a statement that energy 'earns interest' — it is algebra: moving LCOE (a constant) outside the revenue sum leaves sum[E_t/(1+r)^t].
A10: Timing convention: capex at end of year 0 (= COD, interest during construction already in capex), operating cash flows at the end of years 1..life.
A11: EXERCISES (see Lesson m10-l07)
A12: 1. Base case: confirm LCOE = 1.764 US cents/kWh at 6.2% WACC. Compare with the CRF shortcut (1.634) and explain the gap (degradation and opex escalation).
A13: 2. Change WACC to 6.45% and confirm LCOE = 1.800 US cents/kWh — the bid tariff in the project-finance model. Why does LCOE at the project IRR equal a flat tariff?
A14: 3. Find the capex (USD m) that brings LCOE to 1.50 US cents/kWh at 6.2% (use Goal Seek on Results LCOE by changing Inputs capex).
... A19: Currency convention: USD for IPP economics, KWD for ministry budgets; assumed 1 KWD = 3.25 USD (change in Inputs where shown).

Sheet Inputs
A1: Inputs — LCOE model
A2: Change only the yellow cells.
A4: Input | B4: Value | C4: Unit | D4: Note / typical range
A5: Plant AC capacity | B5: 1100 | C5: MWac
A6: Plant DC capacity | B6: 1430 | C6: MWp | D6: DC/AC 1.2–1.35 typical for trackers in the Gulf
A7: Specific yield, year 1 (P50) | B7: 2100 | C7: kWh/kWp/yr | D7: Single-axis bifacial, Kuwait-like: ~1,950–2,250; fixed tilt ~1,750–1,900
A8: Annual degradation (from year 2) | B8: 0.004 | C8: %/yr | D8: 0.3–0.5 %/yr n-type; check module warranty
A9: Total capex at COD (incl. IDC, dev, grid) | B9: 560 | C9: USD m | D9: See Lesson 3 breakdown
A10: Opex, year 1 (O&M, cleaning, insurance, SPV) | B10: 7.5 | C10: USD m/yr | D10: USD 5–9/kWac/yr in Gulf benchmarks
A11: Opex escalation | B11: 0.02 | C11: %/yr
A12: Discount rate (nominal WACC) | B12: 0.062 | C12: %/yr | D12: Must match the cash-flow basis: nominal with nominal, real with real
A13: Economic life / PPA term | B13: 30 | C13: years | D13: Max 40 in this sheet
A14: Exchange rate | B14: 3.25 | C14: USD per KWD
A17: Derived | B17: Value | C17: Unit | D17: How it is calculated
A18: DC/AC ratio | B18: ='Inputs'!$B$6/'Inputs'!$B$5 | C18: –
A19: Energy year 1 | B19: ='Inputs'!$B$6*'Inputs'!$B$7/1000 | C19: GWh | D19: MWp x kWh/kWp / 1000
A20: Capacity factor (AC basis) | B20: =('Inputs'!$B$6*'Inputs'!$B$7/1000)/('Inputs'!$B$5*8.76) | C20: % | D20: E / (P_AC x 8,760 h)
A21: Capex per Wp (DC) | B21: ='Inputs'!$B$9/'Inputs'!$B$6 | C21: USD/Wp
A22: Capex per kWac | B22: ='Inputs'!$B$9*1000/'Inputs'!$B$5 | C22: USD/kWac

Sheet Calc
A1: Annual calculation (do not edit)
A2: Rows: year 0 (capex) to year 40; the life switch zeroes years beyond the economic life.
A4: Year | B4: Operating flag | C4: Energy (GWh) | D4: Opex (USD m) | E4: Capex (USD m) | F4: Discount factor | G4: PV energy (GWh) | H4: PV cost (USD m)
A5: 0 | B5: =IF(AND(A5>=1,A5<='Inputs'!$B$13),1,0) | C5: =B5*'Inputs'!$B$19*(1-'Inputs'!$B$8)^(A5-1) | D5: =B5*'Inputs'!$B$10*(1+'Inputs'!$B$11)^(A5-1) | E5: =IF(A5=0,'Inputs'!$B$9,0) | F5: =1/(1+'Inputs'!$B$12)^A5 | G5: =C5*F5 | H5: =(D5+E5)*F5
A6: 1 | B6: =IF(AND(A6>=1,A6<='Inputs'!$B$13),1,0) | C6: =B6*'Inputs'!$B$19*(1-'Inputs'!$B$8)^(A6-1) | D6: =B6*'Inputs'!$B$10*(1+'Inputs'!$B$11)^(A6-1) | E6: =IF(A6=0,'Inputs'!$B$9,0) | F6: =1/(1+'Inputs'!$B$12)^A6 | G6: =C6*F6 | H6: =(D6+E6)*F6
A7: 2 | B7: =IF(AND(A7>=1,A7<='Inputs'!$B$13),1,0) | C7: =B7*'Inputs'!$B$19*(1-'Inputs'!$B$8)^(A7-1) | D7: =B7*'Inputs'!$B$10*(1+'Inputs'!$B$11)^(A7-1) | E7: =IF(A7=0,'Inputs'!$B$9,0) | F7: =1/(1+'Inputs'!$B$12)^A7 | G7: =C7*F7 | H7: =(D7+E7)*F7
A8: 3 | B8: =IF(AND(A8>=1,A8<='Inputs'!$B$13),1,0) | C8: =B8*'Inputs'!$B$19*(1-'Inputs'!$B$8)^(A8-1) | D8: =B8*'Inputs'!$B$10*(1+'Inputs'!$B$11)^(A8-1) | E8: =IF(A8=0,'Inputs'!$B$9,0) | F8: =1/(1+'Inputs'!$B$12)^A8 | G8: =C8*F8 | H8: =(D8+E8)*F8
A9: 4 | B9: =IF(AND(A9>=1,A9<='Inputs'!$B$13),1,0) | C9: =B9*'Inputs'!$B$19*(1-'Inputs'!$B$8)^(A9-1) | D9: =B9*'Inputs'!$B$10*(1+'Inputs'!$B$11)^(A9-1) | E9: =IF(A9=0,'Inputs'!$B$9,0) | F9: =1/(1+'Inputs'!$B$12)^A9 | G9: =C9*F9 | H9: =(D9+E9)*F9
A10: 5 | B10: =IF(AND(A10>=1,A10<='Inputs'!$B$13),1,0) | C10: =B10*'Inputs'!$B$19*(1-'Inputs'!$B$8)^(A10-1) | D10: =B10*'Inputs'!$B$10*(1+'Inputs'!$B$11)^(A10-1) | E10: =IF(A10=0,'Inputs'!$B$9,0) | F10: =1/(1+'Inputs'!$B$12)^A10 | G10: =C10*F10 | H10: =(D10+E10)*F10
A11: 6 | B11: =IF(AND(A11>=1,A11<='Inputs'!$B$13),1,0) | C11: =B11*'Inputs'!$B$19*(1-'Inputs'!$B$8)^(A11-1) | D11: =B11*'Inputs'!$B$10*(1+'Inputs'!$B$11)^(A11-1) | E11: =IF(A11=0,'Inputs'!$B$9,0) | F11: =1/(1+'Inputs'!$B$12)^A11 | G11: =C11*F11 | H11: =(D11+E11)*F11
A12: 7 | B12: =IF(AND(A12>=1,A12<='Inputs'!$B$13),1,0) | C12: =B12*'Inputs'!$B$19*(1-'Inputs'!$B$8)^(A12-1) | D12: =B12*'Inputs'!$B$10*(1+'Inputs'!$B$11)^(A12-1) | E12: =IF(A12=0,'Inputs'!$B$9,0) | F12: =1/(1+'Inputs'!$B$12)^A12 | G12: =C12*F12 | H12: =(D12+E12)*F12
A13: 8 | B13: =IF(AND(A13>=1,A13<='Inputs'!$B$13),1,0) | C13: =B13*'Inputs'!$B$19*(1-'Inputs'!$B$8)^(A13-1) | D13: =B13*'Inputs'!$B$10*(1+'Inputs'!$B$11)^(A13-1) | E13: =IF(A13=0,'Inputs'!$B$9,0) | F13: =1/(1+'Inputs'!$B$12)^A13 | G13: =C13*F13 | H13: =(D13+E13)*F13
A14: 9 | B14: =IF(AND(A14>=1,A14<='Inputs'!$B$13),1,0) | C14: =B14*'Inputs'!$B$19*(1-'Inputs'!$B$8)^(A14-1) | D14: =B14*'Inputs'!$B$10*(1+'Inputs'!$B$11)^(A14-1) | E14: =IF(A14=0,'Inputs'!$B$9,0) | F14: =1/(1+'Inputs'!$B$12)^A14 | G14: =C14*F14 | H14: =(D14+E14)*F14
A15: 10 | B15: =IF(AND(A15>=1,A15<='Inputs'!$B$13),1,0) | C15: =B15*'Inputs'!$B$19*(1-'Inputs'!$B$8)^(A15-1) | D15: =B15*'Inputs'!$B$10*(1+'Inputs'!$B$11)^(A15-1) | E15: =IF(A15=0,'Inputs'!$B$9,0) | F15: =1/(1+'Inputs'!$B$12)^A15 | G15: =C15*F15 | H15: =(D15+E15)*F15
A16: 11 | B16: =IF(AND(A16>=1,A16<='Inputs'!$B$13),1,0) | C16: =B16*'Inputs'!$B$19*(1-'Inputs'!$B$8)^(A16-1) | D16: =B16*'Inputs'!$B$10*(1+'Inputs'!$B$11)^(A16-1) | E16: =IF(A16=0,'Inputs'!$B$9,0) | F16: =1/(1+'Inputs'!$B$12)^A16 | G16: =C16*F16 | H16: =(D16+E16)*F16
... A45: 40 | B45: =IF(AND(A45>=1,A45<='Inputs'!$B$13),1,0) | C45: =B45*'Inputs'!$B$19*(1-'Inputs'!$B$8)^(A45-1) | D45: =B45*'Inputs'!$B$10*(1+'Inputs'!$B$11)^(A45-1) | E45: =IF(A45=0,'Inputs'!$B$9,0) | F45: =1/(1+'Inputs'!$B$12)^A45 | G45: =C45*F45 | H45: =(D45+E45)*F45
A46: Total | C46: =SUM(C5:C45) | D46: =SUM(D5:D45) | E46: =SUM(E5:E45) | G46: =SUM(G5:G45) | H46: =SUM(H5:H45)

Sheet Results
A1: Results — LCOE
A2: LCOE = PV(costs) / PV(energy)
A4: Result | B4: Value | C4: Unit | D4: How it is calculated
A5: PV of costs (capex + opex) | B5: =Calc!H46 | C5: USD m
A6: PV of energy ('discounted GWh') | B6: =Calc!G46 | C6: GWh
A7: LCOE | B7: =B5/B6 | C7: USD/kWh | D7: USD m / GWh = USD/kWh
A8: LCOE | B8: =B7*1000 | C8: USD/MWh
A9: LCOE | B9: =B7*100 | C9: US cents/kWh
A10: LCOE | B10: =B7/'Inputs'!$B$14*1000 | C10: fils/kWh | D10: 1 KWD = 1,000 fils
A12: CRF shortcut (no degradation, flat opex) | B12: Value | C12: Unit | D12: How it is calculated
A13: Capital recovery factor | B13: ='Inputs'!$B$12*(1+'Inputs'!$B$12)^'Inputs'!$B$13/((1+'Inputs'!$B$12)^'Inputs'!$B$13-1) | C13: 1/yr | D13: CRF = r(1+r)^n / ((1+r)^n - 1)
A14: Annualised capital charge | B14: ='Inputs'!$B$9*B13 | C14: USD m/yr
A15: Simple LCOE = (Capex x CRF + Opex1)/E1 | B15: =(B14+'Inputs'!$B$10)/'Inputs'!$B$19*100 | C15: US cents/kWh | D15: Understates true LCOE when output degrades and opex escalates
A16: Levelized (annuity-equivalent) energy | B16: =B6*B13 | C16: GWh/yr
A17: Levelized opex | B17: =(B5-'Inputs'!$B$9)*B13 | C17: USD m/yr
A18: Exact LCOE via levelized terms (check) | B18: =(B14+B17)/B16*100 | C18: US cents/kWh | D18: Must equal B9

Sheet Sensitivity
A1: Sensitivity — LCOE vs WACC and tornado
A2: Each cell recomputes the full discounted sum with SUMPRODUCT (no data tables needed).
A4: WACC | B4: LCOE (US cents/kWh)
A5: 0.04 | B5: =('Inputs'!$B$9*1+1*SUMPRODUCT(Calc!$D$5:$D$45,1/(1+A5)^Calc!$A$5:$A$45))/(1*SUMPRODUCT(Calc!$B$5:$B$45*'Inputs'!$B$19*(1-'Inputs'!$B$8)^(Calc!$A$5:$A$45-1),1/(1+A5)^Calc!$A$5:$A$45))*100
A6: 0.05 | B6: =('Inputs'!$B$9*1+1*SUMPRODUCT(Calc!$D$5:$D$45,1/(1+A6)^Calc!$A$5:$A$45))/(1*SUMPRODUCT(Calc!$B$5:$B$45*'Inputs'!$B$19*(1-'Inputs'!$B$8)^(Calc!$A$5:$A$45-1),1/(1+A6)^Calc!$A$5:$A$45))*100
A7: 0.055 | B7: =('Inputs'!$B$9*1+1*SUMPRODUCT(Calc!$D$5:$D$45,1/(1+A7)^Calc!$A$5:$A$45))/(1*SUMPRODUCT(Calc!$B$5:$B$45*'Inputs'!$B$19*(1-'Inputs'!$B$8)^(Calc!$A$5:$A$45-1),1/(1+A7)^Calc!$A$5:$A$45))*100
A8: 0.06 | B8: =('Inputs'!$B$9*1+1*SUMPRODUCT(Calc!$D$5:$D$45,1/(1+A8)^Calc!$A$5:$A$45))/(1*SUMPRODUCT(Calc!$B$5:$B$45*'Inputs'!$B$19*(1-'Inputs'!$B$8)^(Calc!$A$5:$A$45-1),1/(1+A8)^Calc!$A$5:$A$45))*100
A9: 0.062 | B9: =('Inputs'!$B$9*1+1*SUMPRODUCT(Calc!$D$5:$D$45,1/(1+A9)^Calc!$A$5:$A$45))/(1*SUMPRODUCT(Calc!$B$5:$B$45*'Inputs'!$B$19*(1-'Inputs'!$B$8)^(Calc!$A$5:$A$45-1),1/(1+A9)^Calc!$A$5:$A$45))*100
A10: 0.065 | B10: =('Inputs'!$B$9*1+1*SUMPRODUCT(Calc!$D$5:$D$45,1/(1+A10)^Calc!$A$5:$A$45))/(1*SUMPRODUCT(Calc!$B$5:$B$45*'Inputs'!$B$19*(1-'Inputs'!$B$8)^(Calc!$A$5:$A$45-1),1/(1+A10)^Calc!$A$5:$A$45))*100
A11: 0.07 | B11: =('Inputs'!$B$9*1+1*SUMPRODUCT(Calc!$D$5:$D$45,1/(1+A11)^Calc!$A$5:$A$45))/(1*SUMPRODUCT(Calc!$B$5:$B$45*'Inputs'!$B$19*(1-'Inputs'!$B$8)^(Calc!$A$5:$A$45-1),1/(1+A11)^Calc!$A$5:$A$45))*100
A12: 0.08 | B12: =('Inputs'!$B$9*1+1*SUMPRODUCT(Calc!$D$5:$D$45,1/(1+A12)^Calc!$A$5:$A$45))/(1*SUMPRODUCT(Calc!$B$5:$B$45*'Inputs'!$B$19*(1-'Inputs'!$B$8)^(Calc!$A$5:$A$45-1),1/(1+A12)^Calc!$A$5:$A$45))*100
A13: 0.09 | B13: =('Inputs'!$B$9*1+1*SUMPRODUCT(Calc!$D$5:$D$45,1/(1+A13)^Calc!$A$5:$A$45))/(1*SUMPRODUCT(Calc!$B$5:$B$45*'Inputs'!$B$19*(1-'Inputs'!$B$8)^(Calc!$A$5:$A$45-1),1/(1+A13)^Calc!$A$5:$A$45))*100
A14: 0.1 | B14: =('Inputs'!$B$9*1+1*SUMPRODUCT(Calc!$D$5:$D$45,1/(1+A14)^Calc!$A$5:$A$45))/(1*SUMPRODUCT(Calc!$B$5:$B$45*'Inputs'!$B$19*(1-'Inputs'!$B$8)^(Calc!$A$5:$A$45-1),1/(1+A14)^Calc!$A$5:$A$45))*100
A16: Tornado (one variable at a time; others at base)
A17: Variable | B17: Low case | C17: High case | D17: LCOE at low | E17: LCOE at high | F17: Swing (abs)
A18: Capex (multiplier) | B18: 0.9 | C18: 1.1 | D18: =('Inputs'!$B$9*B18+1*SUMPRODUCT(Calc!$D$5:$D$45,1/(1+'Inputs'!$B$12)^Calc!$A$5:$A$45))/(1*SUMPRODUCT(Calc!$B$5:$B$45*'Inputs'!$B$19*(1-'Inputs'!$B$8)^(Calc!$A$5:$A$45-1),1/(1+'Inputs'!$B$12)^Calc!$A$5:$A$45))*100 | E18: =('Inputs'!$B$9*C18+1*SUMPRODUCT(Calc!$D$5:$D$45,1/(1+'Inputs'!$B$12)^Calc!$A$5:$A$45))/(1*SUMPRODUCT(Calc!$B$5:$B$45*'Inputs'!$B$19*(1-'Inputs'!$B$8)^(Calc!$A$5:$A$45-1),1/(1+'Inputs'!$B$12)^Calc!$A$5:$A$45))*100 | F18: =ABS(E18-D18)
A19: Specific yield (multiplier) | B19: 1.1 | C19: 0.9 | D19: =('Inputs'!$B$9*1+1*SUMPRODUCT(Calc!$D$5:$D$45,1/(1+'Inputs'!$B$12)^Calc!$A$5:$A$45))/(B19*SUMPRODUCT(Calc!$B$5:$B$45*'Inputs'!$B$19*(1-'Inputs'!$B$8)^(Calc!$A$5:$A$45-1),1/(1+'Inputs'!$B$12)^Calc!$A$5:$A$45))*100 | E19: =('Inputs'!$B$9*1+1*SUMPRODUCT(Calc!$D$5:$D$45,1/(1+'Inputs'!$B$12)^Calc!$A$5:$A$45))/(C19*SUMPRODUCT(Calc!$B$5:$B$45*'Inputs'!$B$19*(1-'Inputs'!$B$8)^(Calc!$A$5:$A$45-1),1/(1+'Inputs'!$B$12)^Calc!$A$5:$A$45))*100 | F19: =ABS(E19-D19)
A20: WACC (absolute) | B20: 0.052 | C20: 0.072 | D20: =('Inputs'!$B$9*1+1*SUMPRODUCT(Calc!$D$5:$D$45,1/(1+B20)^Calc!$A$5:$A$45))/(1*SUMPRODUCT(Calc!$B$5:$B$45*'Inputs'!$B$19*(1-'Inputs'!$B$8)^(Calc!$A$5:$A$45-1),1/(1+B20)^Calc!$A$5:$A$45))*100 | E20: =('Inputs'!$B$9*1+1*SUMPRODUCT(Calc!$D$5:$D$45,1/(1+C20)^Calc!$A$5:$A$45))/(1*SUMPRODUCT(Calc!$B$5:$B$45*'Inputs'!$B$19*(1-'Inputs'!$B$8)^(Calc!$A$5:$A$45-1),1/(1+C20)^Calc!$A$5:$A$45))*100 | F20: =ABS(E20-D20)
A21: Opex (multiplier) | B21: 0.8 | C21: 1.2 | D21: =('Inputs'!$B$9*1+B21*SUMPRODUCT(Calc!$D$5:$D$45,1/(1+'Inputs'!$B$12)^Calc!$A$5:$A$45))/(1*SUMPRODUCT(Calc!$B$5:$B$45*'Inputs'!$B$19*(1-'Inputs'!$B$8)^(Calc!$A$5:$A$45-1),1/(1+'Inputs'!$B$12)^Calc!$A$5:$A$45))*100 | E21: =('Inputs'!$B$9*1+C21*SUMPRODUCT(Calc!$D$5:$D$45,1/(1+'Inputs'!$B$12)^Calc!$A$5:$A$45))/(1*SUMPRODUCT(Calc!$B$5:$B$45*'Inputs'!$B$19*(1-'Inputs'!$B$8)^(Calc!$A$5:$A$45-1),1/(1+'Inputs'!$B$12)^Calc!$A$5:$A$45))*100 | F21: =ABS(E21-D21)
A22: Degradation (absolute) | B22: 0.0025 | C22: 0.007 | D22: =('Inputs'!$B$9*1+1*SUMPRODUCT(Calc!$D$5:$D$45,1/(1+'Inputs'!$B$12)^Calc!$A$5:$A$45))/(1*SUMPRODUCT(Calc!$B$5:$B$45*'Inputs'!$B$19*(1-B22)^(Calc!$A$5:$A$45-1),1/(1+'Inputs'!$B$12)^Calc!$A$5:$A$45))*100 | E22: =('Inputs'!$B$9*1+1*SUMPRODUCT(Calc!$D$5:$D$45,1/(1+'Inputs'!$B$12)^Calc!$A$5:$A$45))/(1*SUMPRODUCT(Calc!$B$5:$B$45*'Inputs'!$B$19*(1-C22)^(Calc!$A$5:$A$45-1),1/(1+'Inputs'!$B$12)^Calc!$A$5:$A$45))*100 | F22: =ABS(E22-D22)
A24: Exercise: sort the rows by Swing (largest first) and draw the tornado as a bar chart (Insert > Bar chart, low and high LCOE minus base).
