Workbook

Sheet README
A1: Project finance model — 1,100 MW PV IPP (Module 10, Lesson 4)
A3: Yellow cells with blue bold text = INPUTS you may change.
A4: Green cells = key RESULTS (formulas — do not overwrite).
A6: WHAT THIS MODEL DOES
A7: A simplified annual lenders'-style model of a solar IPP special purpose vehicle (SPV) selling all output to MEWRE under a 30-year PPA. It builds CFADS (cash flow available for debt service), sizes senior debt by DSCR sculpting subject to a gearing cap, and reports DSCR, LLCR, PLCR, project IRR, equity IRR, NPVs and payback.
A8: Sheets: Inputs -> CashFlow (years 0..40) -> Summary.
A9: Debt sizing logic: target debt service in each loan year = CFADS / target DSCR. The sculpted debt capacity is the present value of that target debt service at the debt interest rate. Debt = MIN(sculpted capacity, max gearing x capex). If the gearing cap binds, actual debt service is scaled down proportionally, so the achieved DSCR is above target.
A10: Simplifications (state them when you present results): no corporate tax, no working capital, no construction-period monthly model (capex incl. IDC is a single year-0 amount), no DSRA cash trapping (the DSRA target is shown for information), no lock-up/cash sweep, P50 energy only. A real lenders' model is monthly/semi-annual and audited by a model auditor.
A11: EXERCISES (see Lesson m10-l07)
A12: 1. Base case at 1.80 US cents/kWh: confirm debt USD 448.0 m (gearing cap binding), min DSCR 1.287x, project IRR 6.45%, equity IRR 8.97%.
A13: 2. Raise max gearing to 90%. Which constraint binds now? What happens to equity IRR and why?
A14: 3. Set tariff to 1.44 US cents/kWh (an 'aggressive' bid 20% below 1.80). Record equity IRR. What capex would the bidder need for a 9% equity IRR (Goal Seek)?
... A19: Currency convention: USD for IPP economics, KWD for ministry budgets; assumed 1 KWD = 3.25 USD (change in Inputs where shown).

Sheet Inputs
A1: Inputs — project finance model
A2: Illustrative base case; change only yellow cells.
A4: Input | B4: Value | C4: Unit | D4: Note / typical range
A5: Plant AC capacity | B5: 1100 | C5: MWac
A6: Plant DC capacity | B6: 1430 | C6: MWp
A7: Specific yield, year 1 (P50) | B7: 2100 | C7: kWh/kWp/yr
A8: Degradation (from year 2) | B8: 0.004 | C8: %/yr
A9: PPA tariff, year 1 | B9: 1.8 | C9: US cents/kWh | D9: Illustrative — NOT a real Kuwait tariff
A10: Tariff indexation | B10: 0 | C10: %/yr | D10: Gulf solar PPAs are often flat in USD terms
A11: Total capex at COD (incl. IDC, fees, DSRA excl.) | B11: 560 | C11: USD m
A12: Opex, year 1 | B12: 7.5 | C12: USD m/yr
A13: Opex escalation | B13: 0.02 | C13: %/yr
A14: PPA term / model life | B14: 30 | C14: years | D14: Kuwait solar IPPs: 30-year PPA (pv magazine, 2025-06-16)
A15: All-in senior debt interest rate | B15: 0.055 | C15: %/yr | D15: Base rate + swap + margin
A16: Debt tenor after COD | B16: 25 | C16: years | D16: Must leave a tail: tenor < PPA term
A17: Target (sizing) DSCR on P50 | B17: 1.25 | C17: x | D17: Contracted solar with strong offtaker: ~1.20–1.35x
A18: Maximum gearing (debt / capex) | B18: 0.8 | C18: % | D18: Typical 70–85% for Gulf solar IPPs
A19: Cost of equity (sponsor hurdle) | B19: 0.09 | C19: %/yr
A20: Discount rate for project NPV (WACC) | B20: 0.062 | C20: %/yr | D20: = 20% x 9% + 80% x 5.5% (no tax)
A21: DSRA requirement | B21: 6 | C21: months of DS
A24: Derived | B24: Value | C24: Unit | D24: How it is calculated
A25: Energy year 1 | B25: ='Inputs'!$B$6*'Inputs'!$B$7/1000 | C25: GWh
A26: Capacity factor (AC) | B26: =('Inputs'!$B$6*'Inputs'!$B$7/1000)/('Inputs'!$B$5*8.76) | C26: %

Sheet CashFlow
A1: Annual cash flow (USD m) — formulas only
A2: Year 0 = COD (capex spent, debt drawn, equity injected).
A4: Year | B4: Op flag | C4: Loan flag | D4: Energy (GWh) | E4: Tariff (USc/kWh) | F4: Revenue | G4: Opex | H4: CFADS | I4: Target DS (CFADS/DSCR) | J4: Debt DF | K4: PV target DS | L4: Opening debt | M4: Interest | N4: Debt service | O4: Principal | P4: Closing debt | Q4: DSCR (x) | R4: DSRA target | S4: Project CF | T4: Equity CF | U4: Cum. project CF | V4: Payback helper
A5: 0 | B5: =IF(AND(A5>=1,A5<='Inputs'!$B$14),1,0) | C5: =IF(AND(A5>=1,A5<='Inputs'!$B$16),1,0) | D5: =B5*'Inputs'!$B$25*(1-'Inputs'!$B$8)^(A5-1) | E5: =B5*'Inputs'!$B$9*(1+'Inputs'!$B$10)^(A5-1) | F5: =D5*E5/100 | G5: =B5*'Inputs'!$B$12*(1+'Inputs'!$B$13)^(A5-1) | H5: =F5-G5 | I5: =C5*H5/'Inputs'!$B$17 | J5: =1/(1+'Inputs'!$B$15)^A5 | K5: =I5*J5 | L5: =0 | M5: =C5*L5*'Inputs'!$B$15 | N5: =I5*Summary!$B$8 | O5: =N5-M5 | P5: =Summary!$B$6 | Q5: =IF(N5>0,H5/N5,"") | R5: =N6*'Inputs'!$B$21/12 | S5: =-'Inputs'!$B$11 | T5: =-('Inputs'!$B$11-Summary!$B$6) | U5: =S5 | V5: =0
A6: 1 | B6: =IF(AND(A6>=1,A6<='Inputs'!$B$14),1,0) | C6: =IF(AND(A6>=1,A6<='Inputs'!$B$16),1,0) | D6: =B6*'Inputs'!$B$25*(1-'Inputs'!$B$8)^(A6-1) | E6: =B6*'Inputs'!$B$9*(1+'Inputs'!$B$10)^(A6-1) | F6: =D6*E6/100 | G6: =B6*'Inputs'!$B$12*(1+'Inputs'!$B$13)^(A6-1) | H6: =F6-G6 | I6: =C6*H6/'Inputs'!$B$17 | J6: =1/(1+'Inputs'!$B$15)^A6 | K6: =I6*J6 | L6: =Summary!$B$6 | M6: =C6*L6*'Inputs'!$B$15 | N6: =I6*Summary!$B$8 | O6: =N6-M6 | P6: =L6-O6 | Q6: =IF(N6>0,H6/N6,"") | R6: =N7*'Inputs'!$B$21/12 | S6: =H6 | T6: =H6-N6 | U6: =U5+S6 | V6: =IF(AND(U5<0,U6>=0),A5-U5/S6,0)
A7: 2 | B7: =IF(AND(A7>=1,A7<='Inputs'!$B$14),1,0) | C7: =IF(AND(A7>=1,A7<='Inputs'!$B$16),1,0) | D7: =B7*'Inputs'!$B$25*(1-'Inputs'!$B$8)^(A7-1) | E7: =B7*'Inputs'!$B$9*(1+'Inputs'!$B$10)^(A7-1) | F7: =D7*E7/100 | G7: =B7*'Inputs'!$B$12*(1+'Inputs'!$B$13)^(A7-1) | H7: =F7-G7 | I7: =C7*H7/'Inputs'!$B$17 | J7: =1/(1+'Inputs'!$B$15)^A7 | K7: =I7*J7 | L7: =P6 | M7: =C7*L7*'Inputs'!$B$15 | N7: =I7*Summary!$B$8 | O7: =N7-M7 | P7: =L7-O7 | Q7: =IF(N7>0,H7/N7,"") | R7: =N8*'Inputs'!$B$21/12 | S7: =H7 | T7: =H7-N7 | U7: =U6+S7 | V7: =IF(AND(U6<0,U7>=0),A6-U6/S7,0)
A8: 3 | B8: =IF(AND(A8>=1,A8<='Inputs'!$B$14),1,0) | C8: =IF(AND(A8>=1,A8<='Inputs'!$B$16),1,0) | D8: =B8*'Inputs'!$B$25*(1-'Inputs'!$B$8)^(A8-1) | E8: =B8*'Inputs'!$B$9*(1+'Inputs'!$B$10)^(A8-1) | F8: =D8*E8/100 | G8: =B8*'Inputs'!$B$12*(1+'Inputs'!$B$13)^(A8-1) | H8: =F8-G8 | I8: =C8*H8/'Inputs'!$B$17 | J8: =1/(1+'Inputs'!$B$15)^A8 | K8: =I8*J8 | L8: =P7 | M8: =C8*L8*'Inputs'!$B$15 | N8: =I8*Summary!$B$8 | O8: =N8-M8 | P8: =L8-O8 | Q8: =IF(N8>0,H8/N8,"") | R8: =N9*'Inputs'!$B$21/12 | S8: =H8 | T8: =H8-N8 | U8: =U7+S8 | V8: =IF(AND(U7<0,U8>=0),A7-U7/S8,0)
A9: 4 | B9: =IF(AND(A9>=1,A9<='Inputs'!$B$14),1,0) | C9: =IF(AND(A9>=1,A9<='Inputs'!$B$16),1,0) | D9: =B9*'Inputs'!$B$25*(1-'Inputs'!$B$8)^(A9-1) | E9: =B9*'Inputs'!$B$9*(1+'Inputs'!$B$10)^(A9-1) | F9: =D9*E9/100 | G9: =B9*'Inputs'!$B$12*(1+'Inputs'!$B$13)^(A9-1) | H9: =F9-G9 | I9: =C9*H9/'Inputs'!$B$17 | J9: =1/(1+'Inputs'!$B$15)^A9 | K9: =I9*J9 | L9: =P8 | M9: =C9*L9*'Inputs'!$B$15 | N9: =I9*Summary!$B$8 | O9: =N9-M9 | P9: =L9-O9 | Q9: =IF(N9>0,H9/N9,"") | R9: =N10*'Inputs'!$B$21/12 | S9: =H9 | T9: =H9-N9 | U9: =U8+S9 | V9: =IF(AND(U8<0,U9>=0),A8-U8/S9,0)
A10: 5 | B10: =IF(AND(A10>=1,A10<='Inputs'!$B$14),1,0) | C10: =IF(AND(A10>=1,A10<='Inputs'!$B$16),1,0) | D10: =B10*'Inputs'!$B$25*(1-'Inputs'!$B$8)^(A10-1) | E10: =B10*'Inputs'!$B$9*(1+'Inputs'!$B$10)^(A10-1) | F10: =D10*E10/100 | G10: =B10*'Inputs'!$B$12*(1+'Inputs'!$B$13)^(A10-1) | H10: =F10-G10 | I10: =C10*H10/'Inputs'!$B$17 | J10: =1/(1+'Inputs'!$B$15)^A10 | K10: =I10*J10 | L10: =P9 | M10: =C10*L10*'Inputs'!$B$15 | N10: =I10*Summary!$B$8 | O10: =N10-M10 | P10: =L10-O10 | Q10: =IF(N10>0,H10/N10,"") | R10: =N11*'Inputs'!$B$21/12 | S10: =H10 | T10: =H10-N10 | U10: =U9+S10 | V10: =IF(AND(U9<0,U10>=0),A9-U9/S10,0)
A11: 6 | B11: =IF(AND(A11>=1,A11<='Inputs'!$B$14),1,0) | C11: =IF(AND(A11>=1,A11<='Inputs'!$B$16),1,0) | D11: =B11*'Inputs'!$B$25*(1-'Inputs'!$B$8)^(A11-1) | E11: =B11*'Inputs'!$B$9*(1+'Inputs'!$B$10)^(A11-1) | F11: =D11*E11/100 | G11: =B11*'Inputs'!$B$12*(1+'Inputs'!$B$13)^(A11-1) | H11: =F11-G11 | I11: =C11*H11/'Inputs'!$B$17 | J11: =1/(1+'Inputs'!$B$15)^A11 | K11: =I11*J11 | L11: =P10 | M11: =C11*L11*'Inputs'!$B$15 | N11: =I11*Summary!$B$8 | O11: =N11-M11 | P11: =L11-O11 | Q11: =IF(N11>0,H11/N11,"") | R11: =N12*'Inputs'!$B$21/12 | S11: =H11 | T11: =H11-N11 | U11: =U10+S11 | V11: =IF(AND(U10<0,U11>=0),A10-U10/S11,0)
A12: 7 | B12: =IF(AND(A12>=1,A12<='Inputs'!$B$14),1,0) | C12: =IF(AND(A12>=1,A12<='Inputs'!$B$16),1,0) | D12: =B12*'Inputs'!$B$25*(1-'Inputs'!$B$8)^(A12-1) | E12: =B12*'Inputs'!$B$9*(1+'Inputs'!$B$10)^(A12-1) | F12: =D12*E12/100 | G12: =B12*'Inputs'!$B$12*(1+'Inputs'!$B$13)^(A12-1) | H12: =F12-G12 | I12: =C12*H12/'Inputs'!$B$17 | J12: =1/(1+'Inputs'!$B$15)^A12 | K12: =I12*J12 | L12: =P11 | M12: =C12*L12*'Inputs'!$B$15 | N12: =I12*Summary!$B$8 | O12: =N12-M12 | P12: =L12-O12 | Q12: =IF(N12>0,H12/N12,"") | R12: =N13*'Inputs'!$B$21/12 | S12: =H12 | T12: =H12-N12 | U12: =U11+S12 | V12: =IF(AND(U11<0,U12>=0),A11-U11/S12,0)
A13: 8 | B13: =IF(AND(A13>=1,A13<='Inputs'!$B$14),1,0) | C13: =IF(AND(A13>=1,A13<='Inputs'!$B$16),1,0) | D13: =B13*'Inputs'!$B$25*(1-'Inputs'!$B$8)^(A13-1) | E13: =B13*'Inputs'!$B$9*(1+'Inputs'!$B$10)^(A13-1) | F13: =D13*E13/100 | G13: =B13*'Inputs'!$B$12*(1+'Inputs'!$B$13)^(A13-1) | H13: =F13-G13 | I13: =C13*H13/'Inputs'!$B$17 | J13: =1/(1+'Inputs'!$B$15)^A13 | K13: =I13*J13 | L13: =P12 | M13: =C13*L13*'Inputs'!$B$15 | N13: =I13*Summary!$B$8 | O13: =N13-M13 | P13: =L13-O13 | Q13: =IF(N13>0,H13/N13,"") | R13: =N14*'Inputs'!$B$21/12 | S13: =H13 | T13: =H13-N13 | U13: =U12+S13 | V13: =IF(AND(U12<0,U13>=0),A12-U12/S13,0)
A14: 9 | B14: =IF(AND(A14>=1,A14<='Inputs'!$B$14),1,0) | C14: =IF(AND(A14>=1,A14<='Inputs'!$B$16),1,0) | D14: =B14*'Inputs'!$B$25*(1-'Inputs'!$B$8)^(A14-1) | E14: =B14*'Inputs'!$B$9*(1+'Inputs'!$B$10)^(A14-1) | F14: =D14*E14/100 | G14: =B14*'Inputs'!$B$12*(1+'Inputs'!$B$13)^(A14-1) | H14: =F14-G14 | I14: =C14*H14/'Inputs'!$B$17 | J14: =1/(1+'Inputs'!$B$15)^A14 | K14: =I14*J14 | L14: =P13 | M14: =C14*L14*'Inputs'!$B$15 | N14: =I14*Summary!$B$8 | O14: =N14-M14 | P14: =L14-O14 | Q14: =IF(N14>0,H14/N14,"") | R14: =N15*'Inputs'!$B$21/12 | S14: =H14 | T14: =H14-N14 | U14: =U13+S14 | V14: =IF(AND(U13<0,U14>=0),A13-U13/S14,0)
A15: 10 | B15: =IF(AND(A15>=1,A15<='Inputs'!$B$14),1,0) | C15: =IF(AND(A15>=1,A15<='Inputs'!$B$16),1,0) | D15: =B15*'Inputs'!$B$25*(1-'Inputs'!$B$8)^(A15-1) | E15: =B15*'Inputs'!$B$9*(1+'Inputs'!$B$10)^(A15-1) | F15: =D15*E15/100 | G15: =B15*'Inputs'!$B$12*(1+'Inputs'!$B$13)^(A15-1) | H15: =F15-G15 | I15: =C15*H15/'Inputs'!$B$17 | J15: =1/(1+'Inputs'!$B$15)^A15 | K15: =I15*J15 | L15: =P14 | M15: =C15*L15*'Inputs'!$B$15 | N15: =I15*Summary!$B$8 | O15: =N15-M15 | P15: =L15-O15 | Q15: =IF(N15>0,H15/N15,"") | R15: =N16*'Inputs'!$B$21/12 | S15: =H15 | T15: =H15-N15 | U15: =U14+S15 | V15: =IF(AND(U14<0,U15>=0),A14-U14/S15,0)
A16: 11 | B16: =IF(AND(A16>=1,A16<='Inputs'!$B$14),1,0) | C16: =IF(AND(A16>=1,A16<='Inputs'!$B$16),1,0) | D16: =B16*'Inputs'!$B$25*(1-'Inputs'!$B$8)^(A16-1) | E16: =B16*'Inputs'!$B$9*(1+'Inputs'!$B$10)^(A16-1) | F16: =D16*E16/100 | G16: =B16*'Inputs'!$B$12*(1+'Inputs'!$B$13)^(A16-1) | H16: =F16-G16 | I16: =C16*H16/'Inputs'!$B$17 | J16: =1/(1+'Inputs'!$B$15)^A16 | K16: =I16*J16 | L16: =P15 | M16: =C16*L16*'Inputs'!$B$15 | N16: =I16*Summary!$B$8 | O16: =N16-M16 | P16: =L16-O16 | Q16: =IF(N16>0,H16/N16,"") | R16: =N17*'Inputs'!$B$21/12 | S16: =H16 | T16: =H16-N16 | U16: =U15+S16 | V16: =IF(AND(U15<0,U16>=0),A15-U15/S16,0)
A17: 12 | B17: =IF(AND(A17>=1,A17<='Inputs'!$B$14),1,0) | C17: =IF(AND(A17>=1,A17<='Inputs'!$B$16),1,0) | D17: =B17*'Inputs'!$B$25*(1-'Inputs'!$B$8)^(A17-1) | E17: =B17*'Inputs'!$B$9*(1+'Inputs'!$B$10)^(A17-1) | F17: =D17*E17/100 | G17: =B17*'Inputs'!$B$12*(1+'Inputs'!$B$13)^(A17-1) | H17: =F17-G17 | I17: =C17*H17/'Inputs'!$B$17 | J17: =1/(1+'Inputs'!$B$15)^A17 | K17: =I17*J17 | L17: =P16 | M17: =C17*L17*'Inputs'!$B$15 | N17: =I17*Summary!$B$8 | O17: =N17-M17 | P17: =L17-O17 | Q17: =IF(N17>0,H17/N17,"") | R17: =N18*'Inputs'!$B$21/12 | S17: =H17 | T17: =H17-N17 | U17: =U16+S17 | V17: =IF(AND(U16<0,U17>=0),A16-U16/S17,0)
A18: 13 | B18: =IF(AND(A18>=1,A18<='Inputs'!$B$14),1,0) | C18: =IF(AND(A18>=1,A18<='Inputs'!$B$16),1,0) | D18: =B18*'Inputs'!$B$25*(1-'Inputs'!$B$8)^(A18-1) | E18: =B18*'Inputs'!$B$9*(1+'Inputs'!$B$10)^(A18-1) | F18: =D18*E18/100 | G18: =B18*'Inputs'!$B$12*(1+'Inputs'!$B$13)^(A18-1) | H18: =F18-G18 | I18: =C18*H18/'Inputs'!$B$17 | J18: =1/(1+'Inputs'!$B$15)^A18 | K18: =I18*J18 | L18: =P17 | M18: =C18*L18*'Inputs'!$B$15 | N18: =I18*Summary!$B$8 | O18: =N18-M18 | P18: =L18-O18 | Q18: =IF(N18>0,H18/N18,"") | R18: =N19*'Inputs'!$B$21/12 | S18: =H18 | T18: =H18-N18 | U18: =U17+S18 | V18: =IF(AND(U17<0,U18>=0),A17-U17/S18,0)
... A44: 39 | B44: =IF(AND(A44>=1,A44<='Inputs'!$B$14),1,0) | C44: =IF(AND(A44>=1,A44<='Inputs'!$B$16),1,0) | D44: =B44*'Inputs'!$B$25*(1-'Inputs'!$B$8)^(A44-1) | E44: =B44*'Inputs'!$B$9*(1+'Inputs'!$B$10)^(A44-1) | F44: =D44*E44/100 | G44: =B44*'Inputs'!$B$12*(1+'Inputs'!$B$13)^(A44-1) | H44: =F44-G44 | I44: =C44*H44/'Inputs'!$B$17 | J44: =1/(1+'Inputs'!$B$15)^A44 | K44: =I44*J44 | L44: =P43 | M44: =C44*L44*'Inputs'!$B$15 | N44: =I44*Summary!$B$8 | O44: =N44-M44 | P44: =L44-O44 | Q44: =IF(N44>0,H44/N44,"") | R44: =N45*'Inputs'!$B$21/12 | S44: =H44 | T44: =H44-N44 | U44: =U43+S44 | V44: =IF(AND(U43<0,U44>=0),A43-U43/S44,0)
A45: 40 | B45: =IF(AND(A45>=1,A45<='Inputs'!$B$14),1,0) | C45: =IF(AND(A45>=1,A45<='Inputs'!$B$16),1,0) | D45: =B45*'Inputs'!$B$25*(1-'Inputs'!$B$8)^(A45-1) | E45: =B45*'Inputs'!$B$9*(1+'Inputs'!$B$10)^(A45-1) | F45: =D45*E45/100 | G45: =B45*'Inputs'!$B$12*(1+'Inputs'!$B$13)^(A45-1) | H45: =F45-G45 | I45: =C45*H45/'Inputs'!$B$17 | J45: =1/(1+'Inputs'!$B$15)^A45 | K45: =I45*J45 | L45: =P44 | M45: =C45*L45*'Inputs'!$B$15 | N45: =I45*Summary!$B$8 | O45: =N45-M45 | P45: =L45-O45 | Q45: =IF(N45>0,H45/N45,"") | R45: =0 | S45: =H45 | T45: =H45-N45 | U45: =U44+S45 | V45: =IF(AND(U44<0,U45>=0),A44-U44/S45,0)
A46: Total | D46: =SUM(D6:D45) | F46: =SUM(F6:F45) | G46: =SUM(G6:G45) | H46: =SUM(H6:H45) | M46: =SUM(M6:M45) | N46: =SUM(N6:N45) | O46: =SUM(O6:O45) | T46: =SUM(T6:T45)

Sheet Summary
A1: Summary — debt sizing, cover ratios and returns
A4: Debt sizing | B4: Value | C4: Unit | D4: How it is calculated
A5: Sculpted debt capacity = PV(CFADS/DSCR) at debt rate | B5: =SUM(CashFlow!$K$5:$K$45) | C5: USD m
A6: Senior debt = MIN(sculpted, gearing cap) | B6: =MIN(B5,'Inputs'!$B$18*'Inputs'!$B$11) | C6: USD m
A7: Gearing-cap debt = max gearing x capex | B7: ='Inputs'!$B$18*'Inputs'!$B$11 | C7: USD m
A8: Debt-service scale factor = debt / sculpted | B8: =B6/B5 | C8: –
A9: Binding constraint | B9: =IF(B5<=B7,"DSCR (sculpting)","Gearing cap")
A10: Achieved gearing | B10: =B6/'Inputs'!$B$11 | C10: %
A11: Equity at COD | B11: ='Inputs'!$B$11-B6 | C11: USD m
A12: Check: debt repaid (sum of principal - debt) | B12: =SUM(CashFlow!$O$5:$O$45)-B6 | C12: USD m | D12: Must be 0.000
A14: Cover ratios | B14: Value | C14: Unit | D14: How it is calculated
A15: Minimum DSCR | B15: =MIN(CashFlow!$Q$5:$Q$45) | C15: x
A16: Average DSCR | B16: =AVERAGE(CashFlow!$Q$5:$Q$45) | C16: x
A17: LLCR at COD = PV(CFADS over loan life)/debt | B17: =SUMPRODUCT(CashFlow!$H$5:$H$45*CashFlow!$C$5:$C$45,CashFlow!$J$5:$J$45)/B6 | C17: x
A18: PLCR at COD = PV(CFADS over project life)/debt | B18: =SUMPRODUCT(CashFlow!$H$5:$H$45*CashFlow!$B$5:$B$45,CashFlow!$J$5:$J$45)/B6 | C18: x
A19: DSRA target at COD (funded by equity/LC) | B19: =CashFlow!R5 | C19: USD m
A21: Returns | B21: Value | C21: Unit | D21: How it is calculated
A22: Project IRR (unlevered, pre-tax) | B22: =IRR(CashFlow!$S$5:$S$45) | C22: %
A23: Equity IRR | B23: =IRR(CashFlow!$T$5:$T$45) | C23: %
A24: Project NPV at WACC | B24: =CashFlow!S5+NPV('Inputs'!$B$20,CashFlow!S6:S45) | C24: USD m
A25: Equity NPV at cost of equity | B25: =CashFlow!T5+NPV('Inputs'!$B$19,CashFlow!T6:T45) | C25: USD m
A26: Simple payback (project) | B26: =SUM(CashFlow!$V$5:$V$45) | C26: years
A27: Revenue year 1 | B27: =CashFlow!F6 | C27: USD m
A28: CFADS year 1 | B28: =CashFlow!H6 | C28: USD m
