Workbook

Sheet README
A1: Tariff bid evaluation — levelized tariff comparison (Module 10, Lesson 5)
A3: Yellow cells with blue bold text = INPUTS you may change.
A4: Green cells = key RESULTS (formulas — do not overwrite).
A6: WHAT THIS MODEL DOES
A7: Compares IPP tariff bids that have different shapes (flat, indexed, front-loaded) on one basis: the levelized tariff LT = sum(T_t x E_t x DF_t) / sum(E_t x DF_t), i.e. the flat tariff that would cost the offtaker the same present value for the same energy. It also shows the present value of payments, ranking at three discount rates, a combined financial/technical score and an 'aggressive bid' flag (deviation from the median levelized tariff).
A8: Sheets: Inputs (evaluation parameters) -> Bids (each bidder's tariff structure, yellow) -> Calc (annual tariffs and discount factors) -> Results.
A9: Evaluation basis is set by the RFP: discount rate, energy profile and whether escalation indices are converted at an assumed rate must be published to bidders BEFORE bids are opened. Changing them afterwards is a procurement-integrity issue.
A10: The 70/30 financial/technical weighting here is ILLUSTRATIVE only. Many Gulf IPP tenders use pass/fail technical compliance followed by lowest levelized tariff; check the actual RFP evaluation criteria.
A11: EXERCISES
A12: 1. At a 7% evaluation rate the ranking is C, A, D, B. Change the main rate to 4% and to 10%. Which pair swaps, and why does front-loading (bid D) win at low rates?
A13: 2. Bid C is 20% below the median: list five questions you would put in a clarification letter before any recommendation.
A14: 3. Change Bid B's escalation to 1.0%/yr. What base tariff would make B equal to A at 7%?
... A18: Currency convention: USD for IPP economics, KWD for ministry budgets; assumed 1 KWD = 3.25 USD (change in Inputs where shown).

Sheet Inputs
A1: Inputs — evaluation parameters
A4: Input | B4: Value | C4: Unit | D4: Note / typical range
A5: Evaluation discount rate (main) | B5: 0.07 | C5: %/yr | D5: Published in the RFP
A6: Alternative rate 1 (sensitivity) | B6: 0.04 | C6: %/yr
A7: Alternative rate 2 (sensitivity) | B7: 0.1 | C7: %/yr
A8: Contract energy year 1 (P50, same for all bids) | B8: 3003 | C8: GWh
A9: Energy degradation profile | B9: 0.004 | C9: %/yr
A10: PPA term | B10: 30 | C10: years
A11: Financial weight | B11: 0.7 | C11: % | D11: Illustrative
A12: Technical weight | B12: 0.3 | C12: %
A13: Aggressive-bid threshold (below median) | B13: -0.15 | C13: % | D13: Triggers abnormally-low-bid clarification

Sheet Bids
A1: Bids — tariff structures (yellow = from bid forms)
A4: Bidder | B4: Tariff yr 1 (USc/kWh) | C4: Indexation (%/yr) | D4: Step after year | E4: Tariff after step (USc/kWh) | F4: Technical score (0–100)
A5: Bid A (flat) | B5: 1.8 | C5: 0 | D5: 30 | E5: 1.8 | F5: 82
A6: Bid B (indexed) | B6: 1.62 | C6: 0.015 | D6: 30 | E6: 1.62 | F6: 85
A7: Bid C (aggressive) | B7: 1.44 | C7: 0 | D7: 30 | E7: 1.44 | F7: 74
A8: Bid D (front-loaded) | B8: 1.95 | C8: 0 | D8: 10 | E8: 1.65 | F8: 88

Sheet Calc
A1: Annual tariffs, energy and discount factors (formulas)
A4: Year | B4: Flag | C4: Energy (GWh) | D4: DF main | E4: DF alt1 | F4: DF alt2 | G4: Tariff A | H4: Tariff B | I4: Tariff C | J4: Tariff D
A5: 1 | B5: =IF(A5<='Inputs'!$B$10,1,0) | C5: =B5*'Inputs'!$B$8*(1-'Inputs'!$B$9)^(A5-1) | D5: =1/(1+'Inputs'!$B$5)^A5 | E5: =1/(1+'Inputs'!$B$6)^A5 | F5: =1/(1+'Inputs'!$B$7)^A5 | G5: =B5*IF(A5<=Bids!$D$5,Bids!$B$5,Bids!$E$5)*(1+Bids!$C$5)^(A5-1) | H5: =B5*IF(A5<=Bids!$D$6,Bids!$B$6,Bids!$E$6)*(1+Bids!$C$6)^(A5-1) | I5: =B5*IF(A5<=Bids!$D$7,Bids!$B$7,Bids!$E$7)*(1+Bids!$C$7)^(A5-1) | J5: =B5*IF(A5<=Bids!$D$8,Bids!$B$8,Bids!$E$8)*(1+Bids!$C$8)^(A5-1)
A6: 2 | B6: =IF(A6<='Inputs'!$B$10,1,0) | C6: =B6*'Inputs'!$B$8*(1-'Inputs'!$B$9)^(A6-1) | D6: =1/(1+'Inputs'!$B$5)^A6 | E6: =1/(1+'Inputs'!$B$6)^A6 | F6: =1/(1+'Inputs'!$B$7)^A6 | G6: =B6*IF(A6<=Bids!$D$5,Bids!$B$5,Bids!$E$5)*(1+Bids!$C$5)^(A6-1) | H6: =B6*IF(A6<=Bids!$D$6,Bids!$B$6,Bids!$E$6)*(1+Bids!$C$6)^(A6-1) | I6: =B6*IF(A6<=Bids!$D$7,Bids!$B$7,Bids!$E$7)*(1+Bids!$C$7)^(A6-1) | J6: =B6*IF(A6<=Bids!$D$8,Bids!$B$8,Bids!$E$8)*(1+Bids!$C$8)^(A6-1)
A7: 3 | B7: =IF(A7<='Inputs'!$B$10,1,0) | C7: =B7*'Inputs'!$B$8*(1-'Inputs'!$B$9)^(A7-1) | D7: =1/(1+'Inputs'!$B$5)^A7 | E7: =1/(1+'Inputs'!$B$6)^A7 | F7: =1/(1+'Inputs'!$B$7)^A7 | G7: =B7*IF(A7<=Bids!$D$5,Bids!$B$5,Bids!$E$5)*(1+Bids!$C$5)^(A7-1) | H7: =B7*IF(A7<=Bids!$D$6,Bids!$B$6,Bids!$E$6)*(1+Bids!$C$6)^(A7-1) | I7: =B7*IF(A7<=Bids!$D$7,Bids!$B$7,Bids!$E$7)*(1+Bids!$C$7)^(A7-1) | J7: =B7*IF(A7<=Bids!$D$8,Bids!$B$8,Bids!$E$8)*(1+Bids!$C$8)^(A7-1)
A8: 4 | B8: =IF(A8<='Inputs'!$B$10,1,0) | C8: =B8*'Inputs'!$B$8*(1-'Inputs'!$B$9)^(A8-1) | D8: =1/(1+'Inputs'!$B$5)^A8 | E8: =1/(1+'Inputs'!$B$6)^A8 | F8: =1/(1+'Inputs'!$B$7)^A8 | G8: =B8*IF(A8<=Bids!$D$5,Bids!$B$5,Bids!$E$5)*(1+Bids!$C$5)^(A8-1) | H8: =B8*IF(A8<=Bids!$D$6,Bids!$B$6,Bids!$E$6)*(1+Bids!$C$6)^(A8-1) | I8: =B8*IF(A8<=Bids!$D$7,Bids!$B$7,Bids!$E$7)*(1+Bids!$C$7)^(A8-1) | J8: =B8*IF(A8<=Bids!$D$8,Bids!$B$8,Bids!$E$8)*(1+Bids!$C$8)^(A8-1)
A9: 5 | B9: =IF(A9<='Inputs'!$B$10,1,0) | C9: =B9*'Inputs'!$B$8*(1-'Inputs'!$B$9)^(A9-1) | D9: =1/(1+'Inputs'!$B$5)^A9 | E9: =1/(1+'Inputs'!$B$6)^A9 | F9: =1/(1+'Inputs'!$B$7)^A9 | G9: =B9*IF(A9<=Bids!$D$5,Bids!$B$5,Bids!$E$5)*(1+Bids!$C$5)^(A9-1) | H9: =B9*IF(A9<=Bids!$D$6,Bids!$B$6,Bids!$E$6)*(1+Bids!$C$6)^(A9-1) | I9: =B9*IF(A9<=Bids!$D$7,Bids!$B$7,Bids!$E$7)*(1+Bids!$C$7)^(A9-1) | J9: =B9*IF(A9<=Bids!$D$8,Bids!$B$8,Bids!$E$8)*(1+Bids!$C$8)^(A9-1)
A10: 6 | B10: =IF(A10<='Inputs'!$B$10,1,0) | C10: =B10*'Inputs'!$B$8*(1-'Inputs'!$B$9)^(A10-1) | D10: =1/(1+'Inputs'!$B$5)^A10 | E10: =1/(1+'Inputs'!$B$6)^A10 | F10: =1/(1+'Inputs'!$B$7)^A10 | G10: =B10*IF(A10<=Bids!$D$5,Bids!$B$5,Bids!$E$5)*(1+Bids!$C$5)^(A10-1) | H10: =B10*IF(A10<=Bids!$D$6,Bids!$B$6,Bids!$E$6)*(1+Bids!$C$6)^(A10-1) | I10: =B10*IF(A10<=Bids!$D$7,Bids!$B$7,Bids!$E$7)*(1+Bids!$C$7)^(A10-1) | J10: =B10*IF(A10<=Bids!$D$8,Bids!$B$8,Bids!$E$8)*(1+Bids!$C$8)^(A10-1)
A11: 7 | B11: =IF(A11<='Inputs'!$B$10,1,0) | C11: =B11*'Inputs'!$B$8*(1-'Inputs'!$B$9)^(A11-1) | D11: =1/(1+'Inputs'!$B$5)^A11 | E11: =1/(1+'Inputs'!$B$6)^A11 | F11: =1/(1+'Inputs'!$B$7)^A11 | G11: =B11*IF(A11<=Bids!$D$5,Bids!$B$5,Bids!$E$5)*(1+Bids!$C$5)^(A11-1) | H11: =B11*IF(A11<=Bids!$D$6,Bids!$B$6,Bids!$E$6)*(1+Bids!$C$6)^(A11-1) | I11: =B11*IF(A11<=Bids!$D$7,Bids!$B$7,Bids!$E$7)*(1+Bids!$C$7)^(A11-1) | J11: =B11*IF(A11<=Bids!$D$8,Bids!$B$8,Bids!$E$8)*(1+Bids!$C$8)^(A11-1)
A12: 8 | B12: =IF(A12<='Inputs'!$B$10,1,0) | C12: =B12*'Inputs'!$B$8*(1-'Inputs'!$B$9)^(A12-1) | D12: =1/(1+'Inputs'!$B$5)^A12 | E12: =1/(1+'Inputs'!$B$6)^A12 | F12: =1/(1+'Inputs'!$B$7)^A12 | G12: =B12*IF(A12<=Bids!$D$5,Bids!$B$5,Bids!$E$5)*(1+Bids!$C$5)^(A12-1) | H12: =B12*IF(A12<=Bids!$D$6,Bids!$B$6,Bids!$E$6)*(1+Bids!$C$6)^(A12-1) | I12: =B12*IF(A12<=Bids!$D$7,Bids!$B$7,Bids!$E$7)*(1+Bids!$C$7)^(A12-1) | J12: =B12*IF(A12<=Bids!$D$8,Bids!$B$8,Bids!$E$8)*(1+Bids!$C$8)^(A12-1)
A13: 9 | B13: =IF(A13<='Inputs'!$B$10,1,0) | C13: =B13*'Inputs'!$B$8*(1-'Inputs'!$B$9)^(A13-1) | D13: =1/(1+'Inputs'!$B$5)^A13 | E13: =1/(1+'Inputs'!$B$6)^A13 | F13: =1/(1+'Inputs'!$B$7)^A13 | G13: =B13*IF(A13<=Bids!$D$5,Bids!$B$5,Bids!$E$5)*(1+Bids!$C$5)^(A13-1) | H13: =B13*IF(A13<=Bids!$D$6,Bids!$B$6,Bids!$E$6)*(1+Bids!$C$6)^(A13-1) | I13: =B13*IF(A13<=Bids!$D$7,Bids!$B$7,Bids!$E$7)*(1+Bids!$C$7)^(A13-1) | J13: =B13*IF(A13<=Bids!$D$8,Bids!$B$8,Bids!$E$8)*(1+Bids!$C$8)^(A13-1)
A14: 10 | B14: =IF(A14<='Inputs'!$B$10,1,0) | C14: =B14*'Inputs'!$B$8*(1-'Inputs'!$B$9)^(A14-1) | D14: =1/(1+'Inputs'!$B$5)^A14 | E14: =1/(1+'Inputs'!$B$6)^A14 | F14: =1/(1+'Inputs'!$B$7)^A14 | G14: =B14*IF(A14<=Bids!$D$5,Bids!$B$5,Bids!$E$5)*(1+Bids!$C$5)^(A14-1) | H14: =B14*IF(A14<=Bids!$D$6,Bids!$B$6,Bids!$E$6)*(1+Bids!$C$6)^(A14-1) | I14: =B14*IF(A14<=Bids!$D$7,Bids!$B$7,Bids!$E$7)*(1+Bids!$C$7)^(A14-1) | J14: =B14*IF(A14<=Bids!$D$8,Bids!$B$8,Bids!$E$8)*(1+Bids!$C$8)^(A14-1)
A15: 11 | B15: =IF(A15<='Inputs'!$B$10,1,0) | C15: =B15*'Inputs'!$B$8*(1-'Inputs'!$B$9)^(A15-1) | D15: =1/(1+'Inputs'!$B$5)^A15 | E15: =1/(1+'Inputs'!$B$6)^A15 | F15: =1/(1+'Inputs'!$B$7)^A15 | G15: =B15*IF(A15<=Bids!$D$5,Bids!$B$5,Bids!$E$5)*(1+Bids!$C$5)^(A15-1) | H15: =B15*IF(A15<=Bids!$D$6,Bids!$B$6,Bids!$E$6)*(1+Bids!$C$6)^(A15-1) | I15: =B15*IF(A15<=Bids!$D$7,Bids!$B$7,Bids!$E$7)*(1+Bids!$C$7)^(A15-1) | J15: =B15*IF(A15<=Bids!$D$8,Bids!$B$8,Bids!$E$8)*(1+Bids!$C$8)^(A15-1)
A16: 12 | B16: =IF(A16<='Inputs'!$B$10,1,0) | C16: =B16*'Inputs'!$B$8*(1-'Inputs'!$B$9)^(A16-1) | D16: =1/(1+'Inputs'!$B$5)^A16 | E16: =1/(1+'Inputs'!$B$6)^A16 | F16: =1/(1+'Inputs'!$B$7)^A16 | G16: =B16*IF(A16<=Bids!$D$5,Bids!$B$5,Bids!$E$5)*(1+Bids!$C$5)^(A16-1) | H16: =B16*IF(A16<=Bids!$D$6,Bids!$B$6,Bids!$E$6)*(1+Bids!$C$6)^(A16-1) | I16: =B16*IF(A16<=Bids!$D$7,Bids!$B$7,Bids!$E$7)*(1+Bids!$C$7)^(A16-1) | J16: =B16*IF(A16<=Bids!$D$8,Bids!$B$8,Bids!$E$8)*(1+Bids!$C$8)^(A16-1)
... A44: 40 | B44: =IF(A44<='Inputs'!$B$10,1,0) | C44: =B44*'Inputs'!$B$8*(1-'Inputs'!$B$9)^(A44-1) | D44: =1/(1+'Inputs'!$B$5)^A44 | E44: =1/(1+'Inputs'!$B$6)^A44 | F44: =1/(1+'Inputs'!$B$7)^A44 | G44: =B44*IF(A44<=Bids!$D$5,Bids!$B$5,Bids!$E$5)*(1+Bids!$C$5)^(A44-1) | H44: =B44*IF(A44<=Bids!$D$6,Bids!$B$6,Bids!$E$6)*(1+Bids!$C$6)^(A44-1) | I44: =B44*IF(A44<=Bids!$D$7,Bids!$B$7,Bids!$E$7)*(1+Bids!$C$7)^(A44-1) | J44: =B44*IF(A44<=Bids!$D$8,Bids!$B$8,Bids!$E$8)*(1+Bids!$C$8)^(A44-1)

Sheet Results
A1: Results — levelized tariff, ranking and flags
A4: Bidder | B4: Levelized tariff @ main (USc/kWh) | C4: PV of payments @ main (USD m) | D4: Rank (1 = cheapest) | E4: Deviation from median | F4: Aggressive-bid flag | G4: Financial score | H4: Technical score | I4: Combined score | J4: Combined rank | K4: LT @ alt1 | L4: Rank @ alt1 | M4: LT @ alt2 | N4: Rank @ alt2 | O4: Nominal undiscounted avg tariff
A5: =Bids!A5 | B5: =SUMPRODUCT(Calc!$G$5:$G$44,Calc!$C$5:$C$44,Calc!$D$5:$D$44)/SUMPRODUCT(Calc!$C$5:$C$44,Calc!$D$5:$D$44) | C5: =SUMPRODUCT(Calc!$G$5:$G$44,Calc!$C$5:$C$44,Calc!$D$5:$D$44)/100 | D5: =RANK(B5,$B$5:$B$8,1) | E5: =B5/MEDIAN($B$5:$B$8)-1 | F5: =IF(E5<='Inputs'!$B$13,"CLARIFY: abnormally low?","ok") | G5: =MIN($B$5:$B$8)/B5*100 | H5: =Bids!F5 | I5: ='Inputs'!$B$11*G5+'Inputs'!$B$12*H5 | J5: =RANK(I5,$I$5:$I$8,0) | K5: =SUMPRODUCT(Calc!$G$5:$G$44,Calc!$C$5:$C$44,Calc!$E$5:$E$44)/SUMPRODUCT(Calc!$C$5:$C$44,Calc!$E$5:$E$44) | L5: =RANK(K5,$K$5:$K$8,1) | M5: =SUMPRODUCT(Calc!$G$5:$G$44,Calc!$C$5:$C$44,Calc!$F$5:$F$44)/SUMPRODUCT(Calc!$C$5:$C$44,Calc!$F$5:$F$44) | N5: =RANK(M5,$M$5:$M$8,1) | O5: =SUM(Calc!$G$5:$G$44)/'Inputs'!$B$10
A6: =Bids!A6 | B6: =SUMPRODUCT(Calc!$H$5:$H$44,Calc!$C$5:$C$44,Calc!$D$5:$D$44)/SUMPRODUCT(Calc!$C$5:$C$44,Calc!$D$5:$D$44) | C6: =SUMPRODUCT(Calc!$H$5:$H$44,Calc!$C$5:$C$44,Calc!$D$5:$D$44)/100 | D6: =RANK(B6,$B$5:$B$8,1) | E6: =B6/MEDIAN($B$5:$B$8)-1 | F6: =IF(E6<='Inputs'!$B$13,"CLARIFY: abnormally low?","ok") | G6: =MIN($B$5:$B$8)/B6*100 | H6: =Bids!F6 | I6: ='Inputs'!$B$11*G6+'Inputs'!$B$12*H6 | J6: =RANK(I6,$I$5:$I$8,0) | K6: =SUMPRODUCT(Calc!$H$5:$H$44,Calc!$C$5:$C$44,Calc!$E$5:$E$44)/SUMPRODUCT(Calc!$C$5:$C$44,Calc!$E$5:$E$44) | L6: =RANK(K6,$K$5:$K$8,1) | M6: =SUMPRODUCT(Calc!$H$5:$H$44,Calc!$C$5:$C$44,Calc!$F$5:$F$44)/SUMPRODUCT(Calc!$C$5:$C$44,Calc!$F$5:$F$44) | N6: =RANK(M6,$M$5:$M$8,1) | O6: =SUM(Calc!$H$5:$H$44)/'Inputs'!$B$10
A7: =Bids!A7 | B7: =SUMPRODUCT(Calc!$I$5:$I$44,Calc!$C$5:$C$44,Calc!$D$5:$D$44)/SUMPRODUCT(Calc!$C$5:$C$44,Calc!$D$5:$D$44) | C7: =SUMPRODUCT(Calc!$I$5:$I$44,Calc!$C$5:$C$44,Calc!$D$5:$D$44)/100 | D7: =RANK(B7,$B$5:$B$8,1) | E7: =B7/MEDIAN($B$5:$B$8)-1 | F7: =IF(E7<='Inputs'!$B$13,"CLARIFY: abnormally low?","ok") | G7: =MIN($B$5:$B$8)/B7*100 | H7: =Bids!F7 | I7: ='Inputs'!$B$11*G7+'Inputs'!$B$12*H7 | J7: =RANK(I7,$I$5:$I$8,0) | K7: =SUMPRODUCT(Calc!$I$5:$I$44,Calc!$C$5:$C$44,Calc!$E$5:$E$44)/SUMPRODUCT(Calc!$C$5:$C$44,Calc!$E$5:$E$44) | L7: =RANK(K7,$K$5:$K$8,1) | M7: =SUMPRODUCT(Calc!$I$5:$I$44,Calc!$C$5:$C$44,Calc!$F$5:$F$44)/SUMPRODUCT(Calc!$C$5:$C$44,Calc!$F$5:$F$44) | N7: =RANK(M7,$M$5:$M$8,1) | O7: =SUM(Calc!$I$5:$I$44)/'Inputs'!$B$10
A8: =Bids!A8 | B8: =SUMPRODUCT(Calc!$J$5:$J$44,Calc!$C$5:$C$44,Calc!$D$5:$D$44)/SUMPRODUCT(Calc!$C$5:$C$44,Calc!$D$5:$D$44) | C8: =SUMPRODUCT(Calc!$J$5:$J$44,Calc!$C$5:$C$44,Calc!$D$5:$D$44)/100 | D8: =RANK(B8,$B$5:$B$8,1) | E8: =B8/MEDIAN($B$5:$B$8)-1 | F8: =IF(E8<='Inputs'!$B$13,"CLARIFY: abnormally low?","ok") | G8: =MIN($B$5:$B$8)/B8*100 | H8: =Bids!F8 | I8: ='Inputs'!$B$11*G8+'Inputs'!$B$12*H8 | J8: =RANK(I8,$I$5:$I$8,0) | K8: =SUMPRODUCT(Calc!$J$5:$J$44,Calc!$C$5:$C$44,Calc!$E$5:$E$44)/SUMPRODUCT(Calc!$C$5:$C$44,Calc!$E$5:$E$44) | L8: =RANK(K8,$K$5:$K$8,1) | M8: =SUMPRODUCT(Calc!$J$5:$J$44,Calc!$C$5:$C$44,Calc!$F$5:$F$44)/SUMPRODUCT(Calc!$C$5:$C$44,Calc!$F$5:$F$44) | N8: =RANK(M8,$M$5:$M$8,1) | O8: =SUM(Calc!$J$5:$J$44)/'Inputs'!$B$10
A11: PV of contract energy @ main rate (GWh, discounted) | C11: =SUMPRODUCT(Calc!$C$5:$C$44,Calc!$D$5:$D$44)
A12: Note: the levelized tariff of a flat bid equals its flat tariff at any discount rate; shaped bids move with the rate. Always publish the evaluation rate in the RFP.
